Workbook

Sheet Sheet1
A1: Country | B1: Payment Mode | C1: Currency | D1: TAT | E1: Supported Modes 1 | F1: Supported Modes | G1: Supported Currencies | H1: Network Participant | I1: Channels | J1: Cutoff & delivery timing | K1: Mandatory data requirements | L1: Supporting Documents | M1: Beneficiary Statement Narrative | N1: Proof of Payment | O1: Notes | P1: Transaction limit per end-user - B2B - Min | Q1: Transaction limit per end-user - B2P - Min | R1: Transaction limit per end-user - P2P - Min | S1: Transaction limit per end-user - P2B - Min | T1: Transaction limit per end-user - B2B - Max | U1: Transaction limit per end-user - B2P - Max | V1: Transaction limit per end-user - P2P - Max | W1: Transaction limit per end-user - P2B - Max | X1: Account Verification
A2: Aland Islands | B2: Foreign Currency Wire Transfer (SWIFT) | C2: USD, EUR, SGD, GBP, AUD, CAD, HKD, JPY, CHF, NZD | D2: T1 | E2: B2B, B2P, P2P, P2B | F2: B2B, B2P, P2P, P2B | G2: USD, EUR, SGD, GBP, AUD, CAD, HKD, JPY, CHF, NZD | H2: Bank | I2: All SWIFT enabled banks in the country | J2: Same-day processing subject to cutoff of 07:30 UTC | K2: Remitter Name, Remitter Account Type, Remitter Identification Type, Remitter Identification Number, Remitter Address, Remitter Country Code, Beneficiary Name, Beneficiary Account Type, Beneficiary Account Number, Beneficiary Country Code, Beneficiary Address (Recommended), Beneficiary City (Recommended), Beneficiary Postcode (Recommended), Routing Code Value 1, Routing Code Type 1 - SWIFT Code, Remit Purpose Code | L2: Remitter Beneficiary Relationship, Nature of Business, Duration of Contract, Commercial Agreement, Current Invoice | M2: Remitter Beneficiary Relationship,Nature of Business,Duration of Contract,Commercial Agreement,Current Invoice | N2: MT103 can be considered as a proof of payment and can be provided on request | O2: WIRES can be sent to all countries except for OFAC listed.MT103 can be provided on request.For foreign currency wire currencies USD, EUR, GBP - NIUM supports both OUR and SHA fee type while for other currencies AUD, CAD, CHF, JPY, NZD, HKD, SGD - NIUM supports only SHA fee typeProcessing of payments to Crimea, Donetsk, Luhansk, Sevastopol regions of Ukraine is prohibited. This list is subject to change. | P2: 0 | Q2: 0 | R2: 0 | S2: 0 | T2: No limit | U2: No limit | V2: No limit | W2: No limit
A3: Albania | B3: Bank Account (SEPA) | C3: EUR | D3: Realtime | E3: B2B, B2P, P2P, P2B | F3: B2B, B2P, P2P, P2B | G3: EUR | H3: Bank | I3: All banks connected with SEPA Network | J3: 1. Real-time for transaction amount <= EUR 100,0002. Same-day for transaction amount > EUR 100,000 subject to cutoff of 14.00 EET | K3: Remitter Name, Remitter Account Type, Remitter Address, Remitter Country Code, Remitter Identification Type, Remitter Identification Number, Remit Purpose Code, Remitter City, Remitter Postcode, Beneficiary Name, Beneficiary Country Code, Beneficiary Account Type, Beneficiary Account Number - IBAN, Routing Code Type 1 - SWIFT CODE, Routing Code Value 1 | L3: Remitter Beneficiary Relationship, Nature of Business, Duration of Contract, Commercial Agreement, Current Invoice | M3: Remitter Name & NIUM appears in the beneficiary statement | N3: Upon request, Proof of Payment for a transaction can be made available. | O3: 1. Coverage includes the EU as well as several Non-EU countries.2. Not all supported countries support Realtime payments3. Few banks in Instant supported countries may not support instant payments and payments will be routed through Standard mode in such cases.4.Certain banks require the complete 11-character SWIFT codeâ€”including the branch identifierâ€”in order to accurately route and successfully process the payment. | P3: EUR 0.01 | Q3: EUR 0.01 | R3: EUR 0.01 | S3: EUR 0.01 | T3: No limit | U3: No limit | V3: No limit | W3: No limit
A4: Albania | B4: Foreign Currency Wire Transfer (SWIFT) | C4: USD, EUR, SGD, GBP, AUD, CAD, HKD, JPY, CHF, NZD | D4: T1 | E4: B2B, B2P, P2P, P2B | F4: B2B, B2P, P2P, P2B | G4: USD, EUR, SGD, GBP, AUD, CAD, HKD, JPY, CHF, NZD | H4: Bank | I4: All SWIFT enabled banks in the country | J4: Same-day processing subject to cutoff of 07:30 UTC | K4: Remitter Name, Remitter Account Type, Remitter Identification Type, Remitter Identification Number, Remitter Address, Remitter Country Code, Beneficiary Name, Beneficiary Account Type, Beneficiary Account Number, Beneficiary Country Code, Beneficiary Address, Beneficiary City, Beneficiary Postcode, Routing Code Value 1, Routing Code Type 1 - SWIFT Code, Remit Purpose Code | L4: Remitter Beneficiary Relationship, Nature of Business, Duration of Contract, Commercial Agreement, Current Invoice | M4: Ultimate Sender Name and narrative details will be passed as part of MT103 message to beneficiary bank.Details available on beneficiary statement will be dependent on beneficiary bank. | N4: MT103 can be considered as a proof of payment and can be provided on request | O4: WIRES can be sent to all countries except for OFAC listed.MT103 can be provided on request.NIUM does not support OUR charge type for CAD currency WIRESProcessing of payments to Crimea, Donetsk, Luhansk, Sevastopol regions of Ukraine is prohibited. This list is subject to change. | P4: 0 | Q4: 0 | R4: 0 | S4: 0 | T4: No limit | U4: No limit | V4: No limit | W4: No limit
A5: Albania | B5: Visa Direct | C5: ALL | D5: Realtime | E5: B2B, B2P, P2P, P2B | F5: B2B, B2P, P2P, P2B | G5: ALL | H5: VISA | J5: 1. 24x7 Availability2. Real-time for Fast fund Enabled (Details on fast-fund enabled countries available on request)3. T+2 for other countries | K5: Remitter Name, Remitter Identification Type, Remitter Identification Number, Remitter Country Code, Beneficiary Card Number, Beneficiary Name, Beneficiary Country Code | O5: For more information, please contact your NIUM account manager team. Additional information and approval from VISA is required before this payout method can be made available.Origination of funds is allowed only from a set of countries as mentioned in the table below.In case the transaction currency does not match the destination card issuer currency, amount will be converted and credited in currency of the card issuer.In few countries, only few banks may allow the transactions.Below additional daily/monthly/yearly limits applicable for P2P transactions whichever reached first Per Day - 30 transactions or USD 10,000 per Beneficiary card Per Week - 50 transactions or USD 25,000 per Beneficiary card Per Month - 150 transactions or USD 50,000 per Beneficiary card.Below additional daily/monthly/yearly limits applicable for B2P/B2B transactions whichever reached first Per Day - 30 transactions or USD 50,000 per Beneficiary card Per Week - 50 transactions or USD 100,000 per Beneficiary card Per Month - 150 transactions or USD 200,000 per Beneficiary card. | P5: 0 | Q5: 0 | R5: 0 | S5: 0 | T5: USD 50,000 | U5: USD 50,000 | V5: USD 2,500 | W5: USD 50,000
A6: Algeria | B6: Foreign Currency Wire Transfer (SWIFT) | C6: USD, EUR, SGD, GBP, AUD, CAD, HKD, JPY, CHF, NZD | D6: T1 | E6: B2B, B2P, P2P, P2B | F6: B2B, B2P, P2P, P2B | G6: USD, EUR, SGD, GBP, AUD, CAD, HKD, JPY, CHF, NZD | H6: Bank | I6: All SWIFT enabled banks in the country | J6: Same-day processing subject to cutoff of 07:30 UTC | K6: Remitter Name, Remitter Account Type, Remitter Identification Type, Remitter Identification Number, Remitter Address, Remitter Country Code, Beneficiary Name, Beneficiary Account Type, Beneficiary Account Number, Beneficiary Country Code, Beneficiary Address, Beneficiary City, Beneficiary Postcode, Routing Code Value 1, Routing Code Type 1 - SWIFT Code, Remit Purpose Code | L6: Remitter Beneficiary Relationship, Nature of Business, Duration of Contract, Commercial Agreement, Current Invoice | M6: Ultimate Sender Name and narrative details will be passed as part of MT103 message to beneficiary bank. Details available on beneficiary statement will be dependent on beneficiary bank. | N6: MT103 can be considered as a proof of payment and can be provided on request | O6: WIRES can be sent to all countries except for OFAC listed.MT103 can be provided on request.NIUM does not support OUR charge type for CAD currency WIRESProcessing of payments to Crimea, Donetsk, Luhansk, Sevastopol regions of Ukraine is prohibited. This list is subject to change. | P6: 0 | Q6: 0 | R6: 0 | S6: 0 | T6: No limit | U6: No limit | V6: No limit | W6: No limit
A7: Algeria | B7: Visa Direct | C7: DZD | D7: T2 | E7: B2B, B2P, P2P, P2B | F7: B2B, B2P, P2P, P2B | G7: DZD | H7: VISA | J7: 1. 24x7 Availability2. Real-time for Fast fund Enabled (Details on fast-fund enabled countries available on request)3. T+2 for other countries | K7: Remitter Name, Remitter Identification Type, Remitter Identification Number, Remitter Country Code, Beneficiary Card Number, Beneficiary Name, Beneficiary Country Code | O7: For more information, please contact your NIUM account manager team. Additional information and approval from VISA is required before this payout method can be made available.Origination of funds is allowed only from a set of countries as mentioned in the table below.In case the transaction currency does not match the destination card issuer currency, amount will be converted and credited in currency of the card issuer.In few countries, only few banks may allow the transactions.Below additional daily/monthly/yearly limits applicable for P2P transactions whichever reached first Per Day - 30 transactions or USD 10,000 per Beneficiary card Per Week - 50 transactions or USD 25,000 per Beneficiary card Per Month - 150 transactions or USD 50,000 per Beneficiary card.Below additional daily/monthly/yearly limits applicable for B2P/B2B transactions whichever reached first Per Day - 30 transactions or USD 50,000 per Beneficiary card Per Week - 50 transactions or USD 100,000 per Beneficiary card Per Month - 150 transactions or USD 200,000 per Beneficiary card. | P7: 0 | Q7: 0 | R7: 0 | S7: 0 | T7: USD 50,000 | U7: USD 50,000 | V7: USD 2,500 | W7: USD 50,000
A8: American Samoa | B8: Bank Account (ACH) | C8: USD | D8: T0 | E8: B2B, B2P, P2P, P2B | F8: B2B, B2P, P2P, P2B | G8: USD | H8: Bank | I8: All banks in USA in the ACH network | J8: Same-day day credit subject to cutoff of 15.00 EST | K8: Remitter Name, Remitter Identification Type, Remitter Account Type, Remitter Identification Number, Remitter Country Code, Remitter City, Remitter Address, Remitter State, Remitter Post Code, Remitter Date of Birth (for Individual), Remit Purpose Code, Beneficiary Account Number, Beneficiary Account Type, Beneficiary Name, Routing Code Type 1(ACH Code), Routing Code Value 1, Beneficiary Address, Beneficiary City, Beneficiary Country Code, Beneficiary Post Code, Beneficiary State | L8: Remitter Beneficiary Relationship, Nature of Business, Duration of Contract, Commercial Agreement, Current Invoice | M8: NIUM Transaction ID is passed on and will be visible in the Beneficiaryâ€™s Statement.Remitter Name and statement narrative will be visible in the Beneficiaryâ€™s Account Statement. Clearing system can limit value of each field visible upto 10 characters. | O8: USD ACH payouts can also be done to below countries if the ACH code is supported as per regulator guidelines. - U. S. Virgin Islands , Guam American Samoa , The Northern Mariana Islands.The status update will be done on end of day basis though the Beneficiary may receive the credit before this. | P8: 0 | Q8: 0 | R8: 0 | S8: 0 | T8: USD 1,000,000 | U8: USD 1,000,000 | V8: USD 1,000,000 | W8: USD 1,000,000
A9: American Samoa | B9: Foreign Currency Wire Transfer (SWIFT) | C9: USD, EUR, SGD, GBP, AUD, CAD, HKD, JPY, CHF, NZD | D9: T1 | E9: B2B, B2P, P2P, P2B | F9: B2B, B2P, P2P, P2B | G9: USD, EUR, SGD, GBP, AUD, CAD, HKD, JPY, CHF, NZD | H9: Bank | I9: All SWIFT enabled banks in the country | J9: Same-day processing subject to cutoff of 07:30 UTC | K9: Remitter Name, Remitter Account Type, Remitter Identification Type, Remitter Identification Number, Remitter Address, Remitter Country Code, Beneficiary Name, Beneficiary Account Type, Beneficiary Account Number, Beneficiary Country Code, Beneficiary Address, Beneficiary City, Beneficiary Postcode, Routing Code Value 1, Routing Code Type 1 - SWIFT Code, Remit Purpose Code | L9: Remitter Beneficiary Relationship, Nature of Business, Duration of Contract, Commercial Agreement, Current Invoice | M9: Ultimate Sender Name and narrative details will be passed as part of MT103 message to beneficiary bank.Details available on beneficiary statement will be dependent on beneficiary bank. | N9: MT103 can be considered as a proof of payment and can be provided on request | O9: WIRES can be sent to all countries except for OFAC listed.MT103 can be provided on request.NIUM does not support OUR charge type for CAD currency WIRESProcessing of payments to Crimea, Donetsk, Luhansk, Sevastopol regions of Ukraine is prohibited. This list is subject to change. | P9: 0 | Q9: 0 | R9: 0 | S9: 0 | T9: No limit | U9: No limit | V9: No limit | W9: No limit
A10: Andorra | B10: Bank Account (SEPA) | C10: EUR | D10: Realtime | E10: B2B, B2P, P2P, P2B | F10: B2B, B2P, P2P, P2B | G10: EUR | H10: Bank | I10: All banks connected with SEPA Network | J10: 1. Real-time for transaction amount <= EUR 100,0002. Same-day for transaction amount > EUR 100,000 subject to cutoff of 14.00 EET | K10: Remitter Name, Remitter Account Type, Remitter Address, Remitter Country Code, Remitter Identification Type, Remitter Identification Number, Remit Purpose Code, Remitter City, Remitter Postcode, Beneficiary Name, Beneficiary Country Code, Beneficiary Account Type, Beneficiary Account Number - IBAN, Routing Code Type 1 - SWIFT CODE, Routing Code Value 1 | L10: Remitter Beneficiary Relationship, Nature of Business, Duration of Contract, Commercial Agreement, Current Invoice | M10: Remitter Name & NIUM appears in the beneficiary statement | N10: Upon request, Proof of Payment for a transaction can be made available. | O10: 1. Coverage includes the EU as well as several Non-EU countries.2. Not all supported countries support Realtime payments3. Few banks in Instant supported countries may not support instant payments and payments will be routed through Standard mode in such cases.4.Certain banks require the complete 11-character SWIFT codeâ€”including the branch identifierâ€”in order to accurately route and successfully process the payment. | P10: EUR 0.01 | Q10: EUR 0.01 | R10: EUR 0.01 | S10: EUR 0.01 | T10: No limit | U10: No limit | V10: No limit | W10: No limit
A11: Andorra | B11: Foreign Currency Wire Transfer (SWIFT) | C11: USD, EUR, SGD, GBP, AUD, CAD, HKD, JPY, CHF, NZD | D11: T1 | E11: B2B, B2P, P2P, P2B | F11: B2B, B2P, P2P, P2B | G11: USD, EUR, SGD, GBP, AUD, CAD, HKD, JPY, CHF, NZD | H11: Bank | I11: All SWIFT enabled banks in the country | J11: Same-day processing subject to cutoff of 07:30 UTC | K11: Remitter Name, Remitter Account Type, Remitter Identification Type, Remitter Identification Number, Remitter Address, Remitter Country Code, Beneficiary Name, Beneficiary Account Type, Beneficiary Account Number, Beneficiary Country Code, Beneficiary Address, Beneficiary City, Beneficiary Postcode, Routing Code Value 1, Routing Code Type 1 - SWIFT Code, Remit Purpose Code | L11: Remitter Beneficiary Relationship, Nature of Business, Duration of Contract, Commercial Agreement, Current Invoice | M11: Ultimate Sender Name and narrative details will be passed as part of MT103 message to beneficiary bank.Details available on beneficiary statement will be dependent on beneficiary bank. | N11: MT103 can be considered as a proof of payment and can be provided on request | O11: WIRES can be sent to all countries except for OFAC listed.MT103 can be provided on request.NIUM does not support OUR charge type for CAD currency WIRESProcessing of payments to Crimea, Donetsk, Luhansk, Sevastopol regions of Ukraine is prohibited. This list is subject to change. | P11: 0 | Q11: 0 | R11: 0 | S11: 0 | T11: No limit | U11: No limit | V11: No limit | W11: No limit
A12: Andorra | B12: Visa Direct | C12: EUR | D12: T2 | E12: B2B, B2P, P2P, P2B | F12: B2B, B2P, P2P, P2B | G12: EUR | H12: VISA | J12: 1. 24x7 Availability2. Real-time for Fast fund Enabled (Details on fast-fund enabled countries available on request)3. T+2 for other countries | K12: Remitter Name, Remitter Identification Type, Remitter Identification Number, Remitter Country Code, Beneficiary Card Number, Beneficiary Name, Beneficiary Country Code | O12: For more information, please contact your NIUM account manager team. Additional information and approval from VISA is required before this payout method can be made available.Origination of funds is allowed only from a set of countries as mentioned in the table below.In case the transaction currency does not match the destination card issuer currency, amount will be converted and credited in currency of the card issuer.In few countries, only few banks may allow the transactions.Below additional daily/monthly/yearly limits applicable for P2P transactions whichever reached first Per Day - 30 transactions or USD 10,000 per Beneficiary card Per Week - 50 transactions or USD 25,000 per Beneficiary card Per Month - 150 transactions or USD 50,000 per Beneficiary card.Below additional daily/monthly/yearly limits applicable for B2P/B2B transactions whichever reached first Per Day - 30 transactions or USD 50,000 per Beneficiary card Per Week - 50 transactions or USD 100,000 per Beneficiary card Per Month - 150 transactions or USD 200,000 per Beneficiary card. | P12: 0 | Q12: 0 | R12: 0 | S12: 0 | T12: USD 50,000 | U12: USD 50,000 | V12: USD 2,500 | W12: USD 50,000
A13: Angola | B13: Foreign Currency Wire Transfer (SWIFT) | C13: USD, EUR, SGD, GBP, AUD, CAD, HKD, JPY, CHF, NZD | D13: T1 | E13: B2B, B2P, P2P, P2B | F13: B2B, B2P, P2P, P2B | G13: USD, EUR, SGD, GBP, AUD, CAD, HKD, JPY, CHF, NZD | H13: Bank | I13: All SWIFT enabled banks in the country | J13: Same-day processing subject to cutoff of 07:30 UTC | K13: Remitter Name, Remitter Account Type, Remitter Identification Type, Remitter Identification Number, Remitter Address, Remitter Country Code, Beneficiary Name, Beneficiary Account Type, Beneficiary Account Number, Beneficiary Country Code, Beneficiary Address (Recommended), Beneficiary City (Recommended), Beneficiary Postcode (Recommended), Routing Code Value 1, Routing Code Type 1 - SWIFT Code, Remit Purpose Code | L13: Remitter Beneficiary Relationship, Nature of Business, Duration of Contract, Commercial Agreement, Current Invoice | M13: Ultimate Sender Name and narrative details will be passed as part of MT103 message to beneficiary bank.Details available on beneficiary statement will be dependent on beneficiary bank. | N13: MT103 can be considered as a proof of payment and can be provided on request | O13: WIRES can be sent to all countries except for OFAC listed.MT103 can be provided on request.For foreign currency wire currencies USD, EUR, GBP - NIUM supports both OUR and SHA fee type while for other currencies AUD, CAD, CHF, JPY, NZD, HKD, SGD - NIUM supports only SHA fee typeProcessing of payments to Crimea, Donetsk, Luhansk, Sevastopol regions of Ukraine is prohibited. This list is subject to change. | P13: 0 | Q13: 0 | R13: 0 | S13: 0 | T13: No limit | U13: No limit | V13: No limit | W13: No limit
A14: Angola | B14: Visa Direct | C14: AOA | D14: T2 | E14: B2B, B2P, P2P, P2B | F14: B2B, B2P, P2P, P2B | G14: AOA | H14: VISA | J14: 1. 24x7 Availability2. Real-time for Fast fund Enabled (Details on fast-fund enabled countries available on request)3. T+2 for other countries | K14: Remitter Name, Remitter Identification Type, Remitter Identification Number, Remitter Country Code, Beneficiary Card Number, Beneficiary Name, Beneficiary Country Code | O14: For more information, please contact your NIUM account manager team. Additional information and approval from VISA is required before this payout method can be made available.Origination of funds is allowed only from a set of countries as mentioned in the table below.In case the transaction currency does not match the destination card issuer currency, amount will be converted and credited in currency of the card issuer.In few countries, only few banks may allow the transactions.Below additional daily/monthly/yearly limits applicable for P2P transactions whichever reached first Per Day - 30 transactions or USD 10,000 per Beneficiary card Per Week - 50 transactions or USD 25,000 per Beneficiary card Per Month - 150 transactions or USD 50,000 per Beneficiary card.Below additional daily/monthly/yearly limits applicable for B2P/B2B transactions whichever reached first Per Day - 30 transactions or USD 50,000 per Beneficiary card Per Week - 50 transactions or USD 100,000 per Beneficiary card Per Month - 150 transactions or USD 200,000 per Beneficiary card. | P14: 0 | Q14: 0 | R14: 0 | S14: 0 | T14: USD 50,000 | U14: USD 50,000 | V14: USD 2,500 | W14: USD 50,000
A15: Anguilla | B15: Foreign Currency Wire Transfer (SWIFT) | C15: USD, EUR, SGD, GBP, AUD, CAD, HKD, JPY, CHF, NZD | D15: T1 | E15: B2B, B2P, P2P, P2B | F15: B2B, B2P, P2P, P2B | G15: USD, EUR, SGD, GBP, AUD, CAD, HKD, JPY, CHF, NZD | H15: Bank | I15: All SWIFT enabled banks in the country | J15: Same-day processing subject to cutoff of 07:30 UTC | K15: Remitter Name, Remitter Account Type, Remitter Identification Type, Remitter Identification Number, Remitter Address, Remitter Country Code, Beneficiary Name, Beneficiary Account Type, Beneficiary Account Number, Beneficiary Country Code, Beneficiary Address, Beneficiary City, Beneficiary Postcode, Routing Code Value 1, Routing Code Type 1 - SWIFT Code, Remit Purpose Code | L15: Remitter Beneficiary Relationship, Nature of Business, Duration of Contract, Commercial Agreement, Current Invoice | M15: Ultimate Sender Name and narrative details will be passed as part of MT103 message to beneficiary bank.Details available on beneficiary statement will be dependent on beneficiary bank. | N15: MT103 can be considered as a proof of payment and can be provided on request | O15: WIRES can be sent to all countries except for OFAC listed.MT103 can be provided on request.NIUM does not support OUR charge type for CAD currency WIRESProcessing of payments to Crimea, Donetsk, Luhansk, Sevastopol regions of Ukraine is prohibited. This list is subject to change. | P15: 0 | Q15: 0 | R15: 0 | S15: 0 | T15: No limit | U15: No limit | V15: No limit | W15: No limit
A16: Antarctica | B16: Foreign Currency Wire Transfer (SWIFT) | C16: USD, EUR, SGD, GBP, AUD, CAD, HKD, JPY, CHF, NZD | D16: T1 | E16: B2B, B2P, P2P, P2B | F16: B2B, B2P, P2P, P2B | G16: USD, EUR, SGD, GBP, AUD, CAD, HKD, JPY, CHF, NZD | H16: Bank | I16: All SWIFT enabled banks in the country | J16: Same-day processing subject to cutoff of 07:30 UTC | K16: Remitter Name, Remitter Account Type, Remitter Identification Type, Remitter Identification Number, Remitter Address, Remitter Country Code, Beneficiary Name, Beneficiary Account Type, Beneficiary Account Number, Beneficiary Country Code, Beneficiary Address, Beneficiary City, Beneficiary Postcode, Routing Code Value 1, Routing Code Type 1 - SWIFT Code, Remit Purpose Code | L16: Remitter Beneficiary Relationship, Nature of Business, Duration of Contract, Commercial Agreement, Current Invoice | M16: Ultimate Sender Name and narrative details will be passed as part of MT103 message to beneficiary bank.Details available on beneficiary statement will be dependent on beneficiary bank. | N16: MT103 can be considered as a proof of payment and can be provided on request | O16: WIRES can be sent to all countries except for OFAC listed.MT103 can be provided on request.NIUM does not support OUR charge type for CAD currency WIRESProcessing of payments to Crimea, Donetsk, Luhansk, Sevastopol regions of Ukraine is prohibited. This list is subject to change. | P16: 0 | Q16: 0 | R16: 0 | S16: 0 | T16: No limit | U16: No limit | V16: No limit | W16: No limit
A17: Antigua | B17: Foreign Currency Wire Transfer (SWIFT) | C17: USD, EUR, SGD, GBP, AUD, CAD, HKD, JPY, CHF, NZD | D17: T1 | E17: B2B, B2P, P2P, P2B | F17: B2B, B2P, P2P, P2B | G17: USD, EUR, SGD, GBP, AUD, CAD, HKD, JPY, CHF, NZD | H17: Bank | I17: All SWIFT enabled banks in the country | J17: Same-day processing subject to cutoff of 07:30 UTC | K17: Remitter Name, Remitter Account Type, Remitter Identification Type, Remitter Identification Number, Remitter Address, Remitter Country Code, Beneficiary Name, Beneficiary Account Type, Beneficiary Account Number, Beneficiary Country Code, Beneficiary Address, Beneficiary City, Beneficiary Postcode, Routing Code Value 1, Routing Code Type 1 - SWIFT Code, Remit Purpose Code | L17: Remitter Beneficiary Relationship, Nature of Business, Duration of Contract, Commercial Agreement, Current Invoice | M17: Ultimate Sender Name and narrative details will be passed as part of MT103 message to beneficiary bank.Details available on beneficiary statement will be dependent on beneficiary bank. | N17: MT103 can be considered as a proof of payment and can be provided on request | O17: WIRES can be sent to all countries except for OFAC listed.MT103 can be provided on request.NIUM does not support OUR charge type for CAD currency WIRESProcessing of payments to Crimea, Donetsk, Luhansk, Sevastopol regions of Ukraine is prohibited. This list is subject to change. | P17: 0 | Q17: 0 | R17: 0 | S17: 0 | T17: No limit | U17: No limit | V17: No limit | W17: No limit
A18: Argentina | B18: Bank Account (ACH) | C18: ARS | D18: Realtime | E18: B2B, B2P, P2P, P2B | F18: B2B, B2P, P2P, P2B | G18: ARS | H18: Partner | I18: All banks in Argentina | J18: REALTIME, 24x7 | K18: Remitter Name, Remitter Identification Type, Remitter Address, Beneficiary Name, Beneficiary Country Code, Beneficiary Account Number, Beneficiary Identification Value, Remitter Account Type, Remitter Identification Number, Remitter Country Code, Beneficiary Account Type, Beneficiary Identification Type, Remit Purpose Code | L18: Remitter Beneficiary Relationship, Nature of Business, Duration of Contract, Commercial Agreement, Current Invoice | M18: Domestic Clearing System limits ability to transfer full remitter information to the Beneficiary. Visibility of Standard Statement Narration is missing | P18: 0 | Q18: 0 | R18: 0 | S18: 0 | T18: No limit | U18: No limit | V18: No limit | W18: No limit
A19: Argentina | B19: Foreign Currency Wire Transfer (SWIFT) | C19: USD, EUR, SGD, GBP, AUD, CAD, HKD, JPY, CHF, NZD | D19: T1 | E19: B2B, B2P, P2P, P2B | F19: B2B, B2P, P2P, P2B | G19: USD, EUR, SGD, GBP, AUD, CAD, HKD, JPY, CHF, NZD | H19: Bank | I19: All SWIFT enabled banks in the country | J19: Same-day processing subject to cutoff of 07:30 UTC | K19: Remitter Name, Remitter Account Type, Remitter Identification Type, Remitter Identification Number, Remitter Address, Remitter Country Code, Beneficiary Name, Beneficiary Account Type, Beneficiary Account Number, Beneficiary Country Code, Beneficiary Address, Beneficiary City, Beneficiary Postcode, Routing Code Value 1, Routing Code Type 1 - SWIFT Code, Remit Purpose Code | L19: Remitter Beneficiary Relationship, Nature of Business, Duration of Contract, Commercial Agreement, Current Invoice | M19: Ultimate Sender Name and narrative details will be passed as part of MT103 message to beneficiary bank.Details available on beneficiary statement will be dependent on beneficiary bank. | N19: MT103 can be considered as a proof of payment and can be provided on request | O19: WIRES can be sent to all countries except for OFAC listed.MT103 can be provided on request.NIUM does not support OUR charge type for CAD currency WIRESProcessing of payments to Crimea, Donetsk, Luhansk, Sevastopol regions of Ukraine is prohibited. This list is subject to change. | P19: 0 | Q19: 0 | R19: 0 | S19: 0 | T19: No limit | U19: No limit | V19: No limit | W19: No limit
A20: Armenia | B20: Foreign Currency Wire Transfer (SWIFT) | C20: USD, EUR, SGD, GBP, AUD, CAD, HKD, JPY, CHF, NZD | D20: T1 | E20: B2B, B2P, P2P, P2B | F20: B2B, B2P, P2P, P2B | G20: USD, EUR, SGD, GBP, AUD, CAD, HKD, JPY, CHF, NZD | H20: Bank | I20: All SWIFT enabled banks in the country | J20: Same-day processing subject to cutoff of 07:30 UTC | K20: Remitter Name, Remitter Account Type, Remitter Identification Type, Remitter Identification Number, Remitter Address, Remitter Country Code, Beneficiary Name, Beneficiary Account Type, Beneficiary Account Number, Beneficiary Country Code, Beneficiary Address (Recommended), Beneficiary City (Recommended), Beneficiary Postcode (Recommended), Routing Code Value 1, Routing Code Type 1 - SWIFT Code, Remit Purpose Code | L20: Remitter Beneficiary Relationship, Nature of Business, Duration of Contract, Commercial Agreement, Current Invoice | M20: Ultimate Sender Name and narrative details will be passed as part of MT103 message to beneficiary bank.Details available on beneficiary statement will be dependent on beneficiary bank. | N20: MT103 can be considered as a proof of payment and can be provided on request | O20: WIRES can be sent to all countries except for OFAC listed.MT103 can be provided on request.For foreign currency wire currencies USD, EUR, GBP - NIUM supports both OUR and SHA fee type while for other currencies AUD, CAD, CHF, JPY, NZD, HKD, SGD - NIUM supports only SHA fee typeProcessing of payments to Crimea, Donetsk, Luhansk, Sevastopol regions of Ukraine is prohibited. This list is subject to change. | P20: 0 | Q20: 0 | R20: 0 | S20: 0 | T20: No limit | U20: No limit | V20: No limit | W20: No limit
A21: Armenia | B21: Visa Direct | C21: AMD | D21: Realtime | E21: B2B, B2P, P2P, P2B | F21: B2B, B2P, P2P, P2B | G21: AMD | H21: VISA | J21: 1. 24x7 Availability2. Real-time for Fast fund Enabled (Details on fast-fund enabled countries available on request)3. T+2 for other countries | K21: Remitter Name, Remitter Identification Type, Remitter Identification Number, Remitter Country Code, Beneficiary Card Number, Beneficiary Name, Beneficiary Country Code | O21: For more information, please contact your NIUM account manager team. Additional information and approval from VISA is required before this payout method can be made available.Origination of funds is allowed only from a set of countries as mentioned in the table below.In case the transaction currency does not match the destination card issuer currency, amount will be converted and credited in currency of the card issuer.In few countries, only few banks may allow the transactions.Below additional daily/monthly/yearly limits applicable for P2P transactions whichever reached first Per Day - 30 transactions or USD 10,000 per Beneficiary card Per Week - 50 transactions or USD 25,000 per Beneficiary card Per Month - 150 transactions or USD 50,000 per Beneficiary card.Below additional daily/monthly/yearly limits applicable for B2P/B2B transactions whichever reached first Per Day - 30 transactions or USD 50,000 per Beneficiary card Per Week - 50 transactions or USD 100,000 per Beneficiary card Per Month - 150 transactions or USD 200,000 per Beneficiary card. | P21: 0 | Q21: 0 | R21: 0 | S21: 0 | T21: USD 50,000 | U21: USD 50,000 | V21: USD 2,500 | W21: USD 50,000
A22: Aruba | B22: Foreign Currency Wire Transfer (SWIFT) | C22: USD, EUR, SGD, GBP, AUD, CAD, HKD, JPY, CHF, NZD | D22: T1 | E22: B2B, B2P, P2P, P2B | F22: B2B, B2P, P2P, P2B | G22: USD, EUR, SGD, GBP, AUD, CAD, HKD, JPY, CHF, NZD | H22: Bank | I22: All SWIFT enabled banks in the country | J22: Same-day processing subject to cutoff of 07:30 UTC | K22: Remitter Name, Remitter Account Type, Remitter Identification Type, Remitter Identification Number, Remitter Address, Remitter Country Code, Beneficiary Name, Beneficiary Account Type, Beneficiary Account Number, Beneficiary Country Code, Beneficiary Address, Beneficiary City, Beneficiary Postcode, Routing Code Value 1, Routing Code Type 1 - SWIFT Code, Remit Purpose Code | L22: Remitter Beneficiary Relationship, Nature of Business, Duration of Contract, Commercial Agreement, Current Invoice | M22: Ultimate Sender Name and narrative details will be passed as part of MT103 message to beneficiary bank.Details available on beneficiary statement will be dependent on beneficiary bank. | N22: MT103 can be considered as a proof of payment and can be provided on request | O22: WIRES can be sent to all countries except for OFAC listed.MT103 can be provided on request.NIUM does not support OUR charge type for CAD currency WIRESProcessing of payments to Crimea, Donetsk, Luhansk, Sevastopol regions of Ukraine is prohibited. This list is subject to change. | P22: 0 | Q22: 0 | R22: 0 | S22: 0 | T22: No limit | U22: No limit | V22: No limit | W22: No limit
A23: Australia | B23: Bank Account (ACH) | C23: AUD | D23: Realtime | E23: B2B, B2P, P2P, P2B | F23: B2B, B2P, P2P, P2B | G23: AUD | H23: Bank | I23: All banks in Australia | J23: Realtime 24x7 for domestic AUD transactions through NPPSame-day credit subject window 08:30 to 19:00 AEST from Monday to Friday | K23: Remitter Name, Remitter Account Type, Remitter Country Code, Remitter Address, Remitter Identification Type, Remitter Identification Number, Beneficiary Name, Beneficiary Country Code, Beneficiary Account Type, Beneficiary Address, Beneficiary City, Beneficiary Account Number, Beneficiary Contact No, Beneficiary Post Code, Routing Code Type 1 - BSB Code, Routing Code Value 1 | L23: Remitter Beneficiary Relationship, Nature of Business, Duration of Contract, Commercial Agreement, Current Invoice | M23: Remitter name and Statement narrative provided by the customer will be visible in the Beneficiary's Statement. | P23: AUD 0.01 | Q23: AUD 0.01 | R23: AUD 0.01 | S23: AUD 0.01 | T23: No limit | U23: No limit | V23: No limit | W23: No limit
A24: Australia | B24: Foreign Currency Wire Transfer (SWIFT) | C24: USD, EUR, SGD, GBP, AUD, CAD, HKD, JPY, CHF, NZD | D24: T1 | E24: B2B, B2P, P2P, P2B | F24: B2B, B2P, P2P, P2B | G24: USD, EUR, SGD, GBP, AUD, CAD, HKD, JPY, CHF, NZD | H24: Bank | I24: All SWIFT enabled banks in the country | J24: Same-day processing subject to cutoff of 07:30 UTC | K24: Remitter Name, Remitter Account Type, Remitter Identification Type, Remitter Identification Number, Remitter Address, Remitter Country Code, Beneficiary Name, Beneficiary Account Type, Beneficiary Account Number, Beneficiary Country Code, Beneficiary Address, Beneficiary City, Beneficiary Postcode, Routing Code Value 1, Routing Code Type 1 - SWIFT Code, Remit Purpose Code | L24: Remitter Beneficiary Relationship, Nature of Business, Duration of Contract, Commercial Agreement, Current Invoice | M24: Ultimate Sender Name and narrative details will be passed as part of MT103 message to beneficiary bank.Details available on beneficiary statement will be dependent on beneficiary bank. | N24: MT103 can be considered as a proof of payment and can be provided on request | O24: WIRES can be sent to all countries except for OFAC listed.MT103 can be provided on request.NIUM does not support OUR charge type for CAD currency WIRESProcessing of payments to Crimea, Donetsk, Luhansk, Sevastopol regions of Ukraine is prohibited. This list is subject to change. | P24: 0 | Q24: 0 | R24: 0 | S24: 0 | T24: No limit | U24: No limit | V24: No limit | W24: No limit
A25: Australia | B25: Proxy (Bank account) | C25: AUD | D25: Realtime | E25: B2B, B2P, P2P, P2B | F25: B2B, B2P, P2P, P2B | G25: AUD | H25: Bank | I25: All NPP enabled Banks | J25: PayID, Real Time - 24x7 | K25: Remitter Name, Remitter Account Type, Remitter Country Code, Remitter Address, Remitter Identification Type, Remitter Identification Number, Beneficiary Name, Beneficiary Country Code, Beneficiary Account Type, Proxy Type, Proxy Value | L25: Remitter Beneficiary Relationship, Nature of Business, Duration of Contract, Commercial Agreement, Current Invoice | M25: Reference number will be visible in the Beneficiary"s bank statement. | O25: Value for proxy type should be a. ABN b. EMAIL c. PHONE NUMBER d. CORPORATE ID | P25: 0 | Q25: 0 | R25: 0 | S25: 0 | T25: No limit | U25: No limit | V25: No limit | W25: No limit | X25: Can verify both the proxy value and the proxy holder's name.
A26: Austria | B26: Bank Account (SEPA) | C26: EUR | D26: Realtime | E26: B2B, B2P, P2P, P2B | F26: B2B, B2P, P2P, P2B | G26: EUR | H26: Bank | I26: All banks connected with SEPA Network | J26: 1. Real-time for transaction amount <= EUR 100,0002. Same-day for transaction amount > EUR 100,000 subject to cutoff of 14.00 EET | K26: Remitter Name, Remitter Account Type, Remitter Address, Remitter Country Code, Remitter Identification Type, Remitter Identification Number, Remit Purpose Code, Remitter City, Remitter Postcode, Beneficiary Name, Beneficiary Country Code, Beneficiary Account Type, Beneficiary Account Number - IBAN, Routing Code Type 1 - SWIFT CODE, Routing Code Value 1 | L26: Remitter Beneficiary Relationship, Nature of Business, Duration of Contract, Commercial Agreement, Current Invoice | M26: Remitter Name & NIUM appears in the beneficiary statement | N26: Upon request, Proof of Payment for a transaction can be made available. | O26: 1. Coverage includes the EU as well as several Non-EU countries.2. Not all supported countries support Realtime payments3. Few banks in Instant supported countries may not support instant payments and payments will be routed through Standard mode in such cases.4.Certain banks require the complete 11-character SWIFT codeâ€”including the branch identifierâ€”in order to accurately route and successfully process the payment. | P26: EUR 0.01 | Q26: EUR 0.01 | R26: EUR 0.01 | S26: EUR 0.01 | T26: No limit | U26: No limit | V26: No limit | W26: No limit
A27: Austria | B27: Foreign Currency Wire Transfer (SWIFT) | C27: USD, EUR, SGD, GBP, AUD, CAD, HKD, JPY, CHF, NZD | D27: T1 | E27: B2B, B2P, P2P, P2B | F27: B2B, B2P, P2P, P2B | G27: USD, EUR, SGD, GBP, AUD, CAD, HKD, JPY, CHF, NZD | H27: Bank | I27: All SWIFT enabled banks in the country | J27: Same-day processing subject to cutoff of 07:30 UTC | K27: Remitter Name, Remitter Account Type, Remitter Identification Type, Remitter Identification Number, Remitter Address, Remitter Country Code, Beneficiary Name, Beneficiary Account Type, Beneficiary Account Number, Beneficiary Country Code, Beneficiary Address, Beneficiary City, Beneficiary Postcode, Routing Code Value 1, Routing Code Type 1 - SWIFT Code, Remit Purpose Code | L27: Remitter Beneficiary Relationship, Nature of Business, Duration of Contract, Commercial Agreement, Current Invoice | M27: Ultimate Sender Name and narrative details will be passed as part of MT103 message to beneficiary bank. Details available on beneficiary statement will be dependent on beneficiary bank. | N27: MT103 can be considered as a proof of payment and can be provided on request | O27: WIRES can be sent to all countries except for OFAC listed.MT103 can be provided on request.NIUM does not support OUR charge type for CAD currency WIRESProcessing of payments to Crimea, Donetsk, Luhansk, Sevastopol regions of Ukraine is prohibited. This list is subject to change. | P27: 0 | Q27: 0 | R27: 0 | S27: 0 | T27: No limit | U27: No limit | V27: No limit | W27: No limit
A28: Austria | B28: Visa Direct | C28: EUR | D28: T2 | E28: B2B, B2P, P2P, P2B | F28: B2B, B2P, P2P, P2B | G28: EUR | H28: VISA | J28: 1. 24x7 Availability2. Real-time for Fast fund Enabled (Details on fast-fund enabled countries available on request)3. T+2 for other countries | K28: Remitter Name, Remitter Identification Type, Remitter Identification Number, Remitter Country Code, Beneficiary Card Number, Beneficiary Name, Beneficiary Country Code | O28: For more information, please contact your NIUM account manager team. Additional information and approval from VISA is required before this payout method can be made available.Origination of funds is allowed only from a set of countries as mentioned in the table below.In case the transaction currency does not match the destination card issuer currency, amount will be converted and credited in currency of the card issuer.In few countries, only few banks may allow the transactions.Below additional daily/monthly/yearly limits applicable for P2P transactions whichever reached first Per Day - 30 transactions or USD 10,000 per Beneficiary card Per Week - 50 transactions or USD 25,000 per Beneficiary card Per Month - 150 transactions or USD 50,000 per Beneficiary card.Below additional daily/monthly/yearly limits applicable for B2P/B2B transactions whichever reached first Per Day - 30 transactions or USD 50,000 per Beneficiary card Per Week - 50 transactions or USD 100,000 per Beneficiary card Per Month - 150 transactions or USD 200,000 per Beneficiary card. | P28: 0 | Q28: 0 | R28: 0 | S28: 0 | T28: USD 50,000 | U28: USD 50,000 | V28: USD 2,500 | W28: USD 50,000
A29: Azerbaijan | B29: Foreign Currency Wire Transfer (SWIFT) | C29: USD, EUR, SGD, GBP, AUD, CAD, HKD, JPY, CHF, NZD | D29: T1 | E29: B2B, B2P, P2P, P2B | F29: B2B, B2P, P2P, P2B | G29: USD, EUR, SGD, GBP, AUD, CAD, HKD, JPY, CHF, NZD | H29: Bank | I29: All SWIFT enabled banks in the country | J29: Same-day processing subject to cutoff of 07:30 UTC | K29: Remitter Name, Remitter Account Type, Remitter Identification Type, Remitter Identification Number, Remitter Address, Remitter Country Code, Beneficiary Name, Beneficiary Account Type, Beneficiary Account Number, Beneficiary Country Code, Beneficiary Address (Recommended), Beneficiary City (Recommended), Beneficiary Postcode (Recommended), Routing Code Value 1, Routing Code Type 1 - SWIFT Code, Remit Purpose Code | L29: Remitter Beneficiary Relationship, Nature of Business, Duration of Contract, Commercial Agreement, Current Invoice | M29: Ultimate Sender Name and narrative details will be passed as part of MT103 message to beneficiary bank.Details available on beneficiary statement will be dependent on beneficiary bank. | N29: MT103 can be considered as a proof of payment and can be provided on request | O29: WIRES can be sent to all countries except for OFAC listed.MT103 can be provided on request.For foreign currency wire currencies USD, EUR, GBP - NIUM supports both OUR and SHA fee type while for other currencies AUD, CAD, CHF, JPY, NZD, HKD, SGD - NIUM supports only SHA fee typeProcessing of payments to Crimea, Donetsk, Luhansk, Sevastopol regions of Ukraine is prohibited. This list is subject to change. | P29: 0 | Q29: 0 | R29: 0 | S29: 0 | T29: No limit | U29: No limit | V29: No limit | W29: No limit
A30: Azerbaijan | B30: Visa Direct | C30: AZN | D30: Realtime | E30: B2B, B2P, P2P, P2B | F30: B2B, B2P, P2P, P2B | G30: AZN | H30: VISA | J30: 1. 24x7 Availability2. Real-time for Fast fund Enabled (Details on fast-fund enabled countries available on request)3. T+2 for other countries | K30: Remitter Name, Remitter Identification Type, Remitter Identification Number, Remitter Country Code, Beneficiary Card Number, Beneficiary Name, Beneficiary Country Code | O30: For more information, please contact your NIUM account manager team. Additional information and approval from VISA is required before this payout method can be made available.Origination of funds is allowed only from a set of countries as mentioned in the table below.In case the transaction currency does not match the destination card issuer currency, amount will be converted and credited in currency of the card issuer.In few countries, only few banks may allow the transactions.Below additional daily/monthly/yearly limits applicable for P2P transactions whichever reached first Per Day - 30 transactions or USD 10,000 per Beneficiary card Per Week - 50 transactions or USD 25,000 per Beneficiary card Per Month - 150 transactions or USD 50,000 per Beneficiary card.Below additional daily/monthly/yearly limits applicable for B2P/B2B transactions whichever reached first Per Day - 30 transactions or USD 50,000 per Beneficiary card Per Week - 50 transactions or USD 100,000 per Beneficiary card Per Month - 150 transactions or USD 200,000 per Beneficiary card. | P30: 0 | Q30: 0 | R30: 0 | S30: 0 | T30: USD 50,000 | U30: USD 50,000 | V30: USD 2,500 | W30: USD 50,000
A31: Bahamas | B31: Foreign Currency Wire Transfer (SWIFT) | C31: USD, EUR, SGD, GBP, AUD, CAD, HKD, JPY, CHF, NZD | D31: T1 | E31: B2B, B2P, P2P, P2B | F31: B2B, B2P, P2P, P2B | G31: USD, EUR, SGD, GBP, AUD, CAD, HKD, JPY, CHF, NZD | H31: Bank | I31: All SWIFT enabled banks in the country | J31: Same-day processing subject to cutoff of 07:30 UTC | K31: Remitter Name, Remitter Account Type, Remitter Identification Type, Remitter Identification Number, Remitter Address, Remitter Country Code, Beneficiary Name, Beneficiary Account Type, Beneficiary Account Number, Beneficiary Country Code, Beneficiary Address, Beneficiary City, Beneficiary Postcode, Routing Code Value 1, Routing Code Type 1 - SWIFT Code, Remit Purpose Code | L31: Remitter Beneficiary Relationship, Nature of Business, Duration of Contract, Commercial Agreement, Current Invoice | M31: Ultimate Sender Name and narrative details will be passed as part of MT103 message to beneficiary bank.Details available on beneficiary statement will be dependent on beneficiary bank. | N31: MT103 can be considered as a proof of payment and can be provided on request | O31: WIRES can be sent to all countries except for OFAC listed.MT103 can be provided on request.NIUM does not support OUR charge type for CAD currency WIRESProcessing of payments to Crimea, Donetsk, Luhansk, Sevastopol regions of Ukraine is prohibited. This list is subject to change. | P31: 0 | Q31: 0 | R31: 0 | S31: 0 | T31: No limit | U31: No limit | V31: No limit | W31: No limit
A32: Bahamas | B32: Visa Direct | C32: BSD | D32: T2 | E32: B2B, B2P, P2P, P2B | F32: B2B, B2P, P2P, P2B | G32: BSD | H32: VISA | J32: 1. 24x7 Availability2. Real-time for Fast fund Enabled (Details on fast-fund enabled countries available on request)3. T+2 for other countries | K32: Remitter Name, Remitter Identification Type, Remitter Identification Number, Remitter Country Code, Beneficiary Card Number, Beneficiary Name, Beneficiary Country Code | O32: For more information, please contact your NIUM account manager team. Additional information and approval from VISA is required before this payout method can be made available.Origination of funds is allowed only from a set of countries as mentioned in the table below.In case the transaction currency does not match the destination card issuer currency, amount will be converted and credited in currency of the card issuer.In few countries, only few banks may allow the transactions.Below additional daily/monthly/yearly limits applicable for P2P transactions whichever reached first Per Day - 30 transactions or USD 10,000 per Beneficiary card Per Week - 50 transactions or USD 25,000 per Beneficiary card Per Month - 150 transactions or USD 50,000 per Beneficiary card.Below additional daily/monthly/yearly limits applicable for B2P/B2B transactions whichever reached first Per Day - 30 transactions or USD 50,000 per Beneficiary card Per Week - 50 transactions or USD 100,000 per Beneficiary card Per Month - 150 transactions or USD 200,000 per Beneficiary card. | P32: 0 | Q32: 0 | R32: 0 | S32: 0 | T32: USD 50,000 | U32: USD 50,000 | V32: USD 2,500 | W32: USD 50,000
A33: Bahrain | B33: Foreign Currency Wire Transfer (SWIFT) | C33: USD, EUR, SGD, GBP, AUD, CAD, HKD, JPY, CHF, NZD | D33: T1 | E33: B2B, B2P, P2P, P2B | F33: B2B, B2P, P2P, P2B | G33: USD, EUR, SGD, GBP, AUD, CAD, HKD, JPY, CHF, NZD | H33: Bank | I33: All SWIFT enabled banks in the country | J33: Same-day processing subject to cutoff of 07:30 UTC | K33: Remitter Name, Remitter Account Type, Remitter Identification Type, Remitter Identification Number, Remitter Address, Remitter Country Code, Beneficiary Name, Beneficiary Account Type, Beneficiary Account Number, Beneficiary Country Code, Beneficiary Address, Beneficiary City, Beneficiary Postcode, Routing Code Value 1, Routing Code Type 1 - SWIFT Code, Remit Purpose Code | L33: Remitter Beneficiary Relationship, Nature of Business, Duration of Contract, Commercial Agreement, Current Invoice | M33: Ultimate Sender Name and narrative details will be passed as part of MT103 message to beneficiary bank.Details available on beneficiary statement will be dependent on beneficiary bank. | N33: MT103 can be considered as a proof of payment and can be provided on request | O33: WIRES can be sent to all countries except for OFAC listed.MT103 can be provided on request.NIUM does not support OUR charge type for CAD currency WIRESProcessing of payments to Crimea, Donetsk, Luhansk, Sevastopol regions of Ukraine is prohibited. This list is subject to change. | P33: 0 | Q33: 0 | R33: 0 | S33: 0 | T33: No limit | U33: No limit | V33: No limit | W33: No limit
A34: Bahrain | B34: Visa Direct | C34: BHD | D34: T2 | E34: B2B, B2P, P2P, P2B | F34: B2B, B2P, P2P, P2B | G34: BHD | H34: VISA | J34: 1. 24x7 Availability2. Real-time for Fast fund Enabled (Details on fast-fund enabled countries available on request)3. T+2 for other countries | K34: Remitter Name, Remitter Identification Type, Remitter Identification Number, Remitter Country Code, Beneficiary Card Number, Beneficiary Name, Beneficiary Country Code | O34: For more information, please contact your NIUM account manager team. Additional information and approval from VISA is required before this payout method can be made available.Origination of funds is allowed only from a set of countries as mentioned in the table below.In case the transaction currency does not match the destination card issuer currency, amount will be converted and credited in currency of the card issuer.In few countries, only few banks may allow the transactions.Below additional daily/monthly/yearly limits applicable for P2P transactions whichever reached first Per Day - 30 transactions or USD 10,000 per Beneficiary card Per Week - 50 transactions or USD 25,000 per Beneficiary card Per Month - 150 transactions or USD 50,000 per Beneficiary card.Below additional daily/monthly/yearly limits applicable for B2P/B2B transactions whichever reached first Per Day - 30 transactions or USD 50,000 per Beneficiary card Per Week - 50 transactions or USD 100,000 per Beneficiary card Per Month - 150 transactions or USD 200,000 per Beneficiary card. | P34: 0 | Q34: 0 | R34: 0 | S34: 0 | T34: USD 50,000 | U34: USD 50,000 | V34: USD 2,500 | W34: USD 50,000
A35: Bailiwick of Guernsey | B35: Bank Account (ACH) | C35: GBP | D35: Realtime | E35: B2B, B2P, P2P, P2B | F35: B2B, B2P, P2P, P2B | G35: GBP | H35: Bank | I35: All banks in UK | J35: 1. Real-time for transaction amount <= GBP 1 Mn2. Same day for transaction amount > GBP 1 Mn subject to cut-off of 15.30 GMT only on working days | K35: Remitter Name, Remitter Account Type, Remitter Address, Remitter Country Code, Remitter Identification Type, Remitter Identificiation Value, Remit Purpose Code, Beneficiary Name, Beneficiary Account Number, Beneficiary Country Code, Beneficiary Account Type, Routing Code Type 1 - Sort Code, Routing Code Value 1 | L35: Remitter Beneficiary Relationship, Nature of Business, Duration of Contract, Commercial Agreement, Current Invoice | M35: NIUM Fintech & Statement Narrative will be visible in the Beneficiarys Bank statement. | O35: The beneficiary account number may be provided in either IBAN or basic account number format. If an IBAN is used, the sort code is typically not required. However, certain banks specifically require an 8-digit account number format to successfully process payments. | P35: GBP 1 | Q35: GBP 1 | R35: GBP 1 | S35: GBP 1 | T35: No limit | U35: No limit | V35: No limit | W35: No limit
A36: Bailiwick of Guernsey | B36: Bank Account (SEPA) | C36: EUR | D36: Realtime | E36: B2B, B2P, P2P, P2B | F36: B2B, B2P, P2P, P2B | G36: EUR | H36: Bank | I36: All banks connected with SEPA Network | J36: 1. Real-time for transaction amount <= EUR 100,0002. Same-day for transaction amount > EUR 100,000 subject to cutoff of 14.00 EET | K36: Remitter Name, Remitter Account Type, Remitter Address, Remitter Country Code, Remitter Identification Type, Remitter Identification Number, Remit Purpose Code, Remitter City, Remitter Postcode, Beneficiary Name, Beneficiary Country Code, Beneficiary Account Type, Beneficiary Account Number - IBAN, Routing Code Type 1 - SWIFT CODE, Routing Code Value 1 | L36: Remitter Beneficiary Relationship, Nature of Business, Duration of Contract, Commercial Agreement, Current Invoice | M36: Remitter Name & NIUM appears in the beneficiary statement | N36: Upon request, Proof of Payment for a transaction can be made available. | O36: 1. Coverage includes the EU as well as several Non-EU countries.2. Not all supported countries support Realtime payments3. Few banks in Instant supported countries may not support instant payments and payments will be routed through Standard mode in such cases.4.Certain banks require the complete 11-character SWIFT codeâ€”including the branch identifierâ€”in order to accurately route and successfully process the payment. | P36: EUR 0.01 | Q36: EUR 0.01 | R36: EUR 0.01 | S36: EUR 0.01 | T36: No limit | U36: No limit | V36: No limit | W36: No limit
A37: Bailiwick of Guernsey | B37: Foreign Currency Wire Transfer (SWIFT) | C37: USD, EUR, SGD, AUD, CAD, HKD, JPY, CHF, NZD | D37: T1 | E37: B2B, B2P, P2P, P2B | F37: B2B, B2P, P2P, P2B | G37: USD, EUR, SGD, AUD, CAD, HKD, JPY, CHF, NZD | H37: Bank | I37: All SWIFT enabled banks in the country | J37: Same-day processing subject to cutoff of 07:30 UTC | K37: Remitter Name, Remitter Account Type, Remitter Identification Type, Remitter Identification Number, Remitter Address, Remitter Country Code, Beneficiary Name, Beneficiary Account Type, Beneficiary Account Number, Beneficiary Country Code, Beneficiary Address (Recommended), Beneficiary City (Recommended), Beneficiary Postcode (Recommended), Routing Code Value 1, Routing Code Type 1 - SWIFT Code, Remit Purpose Code | L37: Remitter Beneficiary Relationship, Nature of Business, Duration of Contract, Commercial Agreement, Current Invoice | M37: Ultimate Sender Name and narrative details will be passed as part of MT103 message to beneficiary bank.Details available on beneficiary statement will be dependent on beneficiary bank. | N37: MT103 can be considered as a proof of payment and can be provided on request | O37: WIRES can be sent to all countries except for OFAC listed.MT103 can be provided on request.For foreign currency wire currencies USD, EUR, GBP - NIUM supports both OUR and SHA fee type while for other currencies AUD, CAD, CHF, JPY, NZD, HKD, SGD - NIUM supports only SHA fee typeProcessing of payments to Crimea, Donetsk, Luhansk, Sevastopol regions of Ukraine is prohibited. This list is subject to change. | P37: 0 | Q37: 0 | R37: 0 | S37: 0 | T37: No limit | U37: No limit | V37: No limit | W37: No limit
A38: Bangladesh | B38: Bank Account (ACH) | C38: BDT | D38: T0 | E38: P2P | F38: P2P | G38: BDT | H38: Bank | I38: All banks in Bangladesh | J38: 07:30 to 22:00 local time Sunday to Thursday | K38: Remitter Name, Remitter Identification Type, Remitter Address, Beneficiary Name, Beneficiary Account Number, Beneficiary Contact Number, Routing Code Value 1, Routing Code Value 2, Remitter Account Type, Remitter Identification Number, Remitter Country Code, Beneficiary Account Type, Routing Code Type 1 - SWIFT CODE, Routing Code Type 1 - BRANCH NAME, Beneficiary Address | L38: Remitter Beneficiary Relationship, Nature of Business, Duration of Contract, Commercial Agreement, Current Invoice | M38: Domestic Clearing System limits ability to transfer full remitter information to the Beneficiary. Visibility of Standard Statement Narration is missing. | P38: Not Supported | Q38: Not Supported | R38: BDT 1 | S38: Not Supported | T38: Not Supported | U38: Not Supported | V38: No limit | W38: Not Supported
A39: Bangladesh | B39: Foreign Currency Wire Transfer (SWIFT) | C39: USD, EUR, SGD, GBP, AUD, CAD, HKD, JPY, CHF, NZD | D39: T1 | E39: B2B, B2P, P2P, P2B | F39: B2B, B2P, P2P, P2B | G39: USD, EUR, SGD, GBP, AUD, CAD, HKD, JPY, CHF, NZD | H39: Bank | I39: All SWIFT enabled banks in the country | J39: Same-day processing subject to cutoff of 07:30 UTC | K39: Remitter Name, Remitter Account Type, Remitter Identification Type, Remitter Identification Number, Remitter Address, Remitter Country Code, Beneficiary Name, Beneficiary Account Type, Beneficiary Account Number, Beneficiary Country Code, Beneficiary Address, Beneficiary City, Beneficiary Postcode, Routing Code Value 1, Routing Code Type 1 - SWIFT Code, Remit Purpose Code | L39: Remitter Beneficiary Relationship, Nature of Business, Duration of Contract, Commercial Agreement, Current Invoice | M39: Ultimate Sender Name and narrative details will be passed as part of MT103 message to beneficiary bank.Details available on beneficiary statement will be dependent on beneficiary bank. | N39: MT103 can be considered as a proof of payment and can be provided on request | O39: WIRES can be sent to all countries except for OFAC listed.MT103 can be provided on request.NIUM does not support OUR charge type for CAD currency WIRESProcessing of payments to Crimea, Donetsk, Luhansk, Sevastopol regions of Ukraine is prohibited. This list is subject to change. | P39: 0 | Q39: 0 | R39: 0 | S39: 0 | T39: No limit | U39: No limit | V39: No limit | W39: No limit
A40: Bangladesh | B40: Visa Direct | C40: BDT | D40: Realtime | E40: B2B, B2P, P2P, P2B | F40: B2B, B2P, P2P, P2B | G40: BDT | H40: VISA | J40: 1. 24x7 Availability2. Real-time for Fast fund Enabled (Details on fast-fund enabled countries available on request)3. T+2 for other countries | K40: Remitter Name, Remitter Identification Type, Remitter Identification Number, Remitter Country Code, Beneficiary Card Number, Beneficiary Name, Beneficiary Country Code | O40: For more information, please contact your NIUM account manager team. Additional information and approval from VISA is required before this payout method can be made available.Origination of funds is allowed only from a set of countries as mentioned in the table below.In case the transaction currency does not match the destination card issuer currency, amount will be converted and credited in currency of the card issuer.In few countries, only few banks may allow the transactions.Below additional daily/monthly/yearly limits applicable for P2P transactions whichever reached first Per Day - 30 transactions or USD 10,000 per Beneficiary card Per Week - 50 transactions or USD 25,000 per Beneficiary card Per Month - 150 transactions or USD 50,000 per Beneficiary card.Below additional daily/monthly/yearly limits applicable for B2P/B2B transactions whichever reached first Per Day - 30 transactions or USD 50,000 per Beneficiary card Per Week - 50 transactions or USD 100,000 per Beneficiary card Per Month - 150 transactions or USD 200,000 per Beneficiary card. | P40: 0 | Q40: 0 | R40: 0 | S40: 0 | T40: USD 50,000 | U40: USD 50,000 | V40: USD 2,500 | W40: USD 50,000
A41: Bangladesh | B41: Wallet | C41: BDT | D41: Realtime | E41: P2P | F41: P2P | G41: BDT | H41: Partner | I41: BKASH,ROCKET | J41: Real Time, 24x7 | K41: Remitter Name, Remitter Identification Number, Remitter Address, Remitter Phone Number, Remitter DOB, Beneficiary Name, Beneficiary Wallet ID, Beneficiary Country Code, Routing Code Value 1 (BKASH), Remitter Account Type, Remitter Identification Type, Remitter Country Code, Remitter Nationality, Remit Purpose Code, Beneficiary Account Type, Beneficiary Nationality, Routing Code Type 1 - WALLET, Payout Method - WALLET | L41: Remitter Beneficiary Relationship, Nature of Business, Duration of Contract, Commercial Agreement, Current Invoice | M41: Sender Name will be visible in the Beneficiary"s wallet entry. | O41: Decimals are not accepted.Remitter Country Code cannot be Bangladesh (BD) | P41: Not Supported | Q41: Not Supported | R41: BDT 50 | S41: Not Supported | T41: Not Supported | U41: Not Supported | V41: BDT 50,000 | W41: Not Supported
A42: Barbados | B42: Foreign Currency Wire Transfer (SWIFT) | C42: USD, EUR, SGD, GBP, AUD, CAD, HKD, JPY, CHF, NZD | D42: T1 | E42: B2B, B2P, P2P, P2B | F42: B2B, B2P, P2P, P2B | G42: USD, EUR, SGD, GBP, AUD, CAD, HKD, JPY, CHF, NZD | H42: Bank | I42: All SWIFT enabled banks in the country | J42: Same-day processing subject to cutoff of 07:30 UTC | K42: Remitter Name, Remitter Account Type, Remitter Identification Type, Remitter Identification Number, Remitter Address, Remitter Country Code, Beneficiary Name, Beneficiary Account Type, Beneficiary Account Number, Beneficiary Country Code, Beneficiary Address (Recommended), Beneficiary City (Recommended), Beneficiary Postcode (Recommended), Routing Code Value 1, Routing Code Type 1 - SWIFT Code, Remit Purpose Code | L42: Remitter Beneficiary Relationship, Nature of Business, Duration of Contract, Commercial Agreement, Current Invoice | M42: Ultimate Sender Name and narrative details will be passed as part of MT103 message to beneficiary bank.Details available on beneficiary statement will be dependent on beneficiary bank. | N42: MT103 can be considered as a proof of payment and can be provided on request | O42: WIRES can be sent to all countries except for OFAC listed.MT103 can be provided on request.For foreign currency wire currencies USD, EUR, GBP - NIUM supports both OUR and SHA fee type while for other currencies AUD, CAD, CHF, JPY, NZD, HKD, SGD - NIUM supports only SHA fee typeProcessing of payments to Crimea, Donetsk, Luhansk, Sevastopol regions of Ukraine is prohibited. This list is subject to change. | P42: 0 | Q42: 0 | R42: 0 | S42: 0 | T42: No limit | U42: No limit | V42: No limit | W42: No limit
A43: Belgium | B43: Bank Account (SEPA) | C43: EUR | D43: Realtime | E43: B2B, B2P, P2P, P2B | F43: B2B, B2P, P2P, P2B | G43: EUR | H43: Bank | I43: All banks connected with SEPA Network | J43: 1. Real-time for transaction amount <= EUR 100,0002. Same-day for transaction amount > EUR 100,000 subject to cutoff of 14.00 EET | K43: Remitter Name, Remitter Account Type, Remitter Address, Remitter Country Code, Remitter Identification Type, Remitter Identification Number, Remit Purpose Code, Remitter City, Remitter Postcode, Beneficiary Name, Beneficiary Country Code, Beneficiary Account Type, Beneficiary Account Number - IBAN, Routing Code Type 1 - SWIFT CODE, Routing Code Value 1 | L43: Remitter Beneficiary Relationship, Nature of Business, Duration of Contract, Commercial Agreement, Current Invoice | M43: Remitter Name & NIUM appears in the beneficiary statement | N43: Upon request, Proof of Payment for a transaction can be made available. | O43: 1. Coverage includes the EU as well as several Non-EU countries.2. Not all supported countries support Realtime payments3. Few banks in Instant supported countries may not support instant payments and payments will be routed through Standard mode in such cases.4.Certain banks require the complete 11-character SWIFT codeâ€”including the branch identifierâ€”in order to accurately route and successfully process the payment. | P43: EUR 0.01 | Q43: EUR 0.01 | R43: EUR 0.01 | S43: EUR 0.01 | T43: No limit | U43: No limit | V43: No limit | W43: No limit
A44: Belgium | B44: Foreign Currency Wire Transfer (SWIFT) | C44: USD, EUR, SGD, GBP, AUD, CAD, HKD, JPY, CHF, NZD | D44: T1 | E44: B2B, B2P, P2P, P2B | F44: B2B, B2P, P2P, P2B | G44: USD, EUR, SGD, GBP, AUD, CAD, HKD, JPY, CHF, NZD | H44: Bank | I44: All SWIFT enabled banks in the country | J44: Same-day processing subject to cutoff of 07:30 UTC | K44: Remitter Name, Remitter Account Type, Remitter Identification Type, Remitter Identification Number, Remitter Address, Remitter Country Code, Beneficiary Name, Beneficiary Account Type, Beneficiary Account Number, Beneficiary Country Code, Beneficiary Address (Recommended), Beneficiary City (Recommended), Beneficiary Postcode (Recommended), Routing Code Value 1, Routing Code Type 1 - SWIFT Code, Remit Purpose Code | L44: Remitter Beneficiary Relationship, Nature of Business, Duration of Contract, Commercial Agreement, Current Invoice | M44: Ultimate Sender Name and narrative details will be passed as part of MT103 message to beneficiary bank.Details available on beneficiary statement will be dependent on beneficiary bank. | N44: MT103 can be considered as a proof of payment and can be provided on request | O44: WIRES can be sent to all countries except for OFAC listed.MT103 can be provided on request.For foreign currency wire currencies USD, EUR, GBP - NIUM supports both OUR and SHA fee type while for other currencies AUD, CAD, CHF, JPY, NZD, HKD, SGD - NIUM supports only SHA fee typeProcessing of payments to Crimea, Donetsk, Luhansk, Sevastopol regions of Ukraine is prohibited. This list is subject to change. | P44: 0 | Q44: 0 | R44: 0 | S44: 0 | T44: No limit | U44: No limit | V44: No limit | W44: No limit
A45: Belgium | B45: Visa Direct | C45: EUR | D45: T2 | E45: B2B, B2P, P2P, P2B | F45: B2B, B2P, P2P, P2B | G45: EUR | H45: VISA | J45: 1. 24x7 Availability2. Real-time for Fast fund Enabled (Details on fast-fund enabled countries available on request)3. T+2 for other countries | K45: Remitter Name, Remitter Identification Type, Remitter Identification Number, Remitter Country Code, Beneficiary Card Number, Beneficiary Name, Beneficiary Country Code | O45: For more information, please contact your NIUM account manager team. Additional information and approval from VISA is required before this payout method can be made available.Origination of funds is allowed only from a set of countries as mentioned in the table below.In case the transaction currency does not match the destination card issuer currency, amount will be converted and credited in currency of the card issuer.In few countries, only few banks may allow the transactions.Below additional daily/monthly/yearly limits applicable for P2P transactions whichever reached first Per Day - 30 transactions or USD 10,000 per Beneficiary card Per Week - 50 transactions or USD 25,000 per Beneficiary card Per Month - 150 transactions or USD 50,000 per Beneficiary card.Below additional daily/monthly/yearly limits applicable for B2P/B2B transactions whichever reached first Per Day - 30 transactions or USD 50,000 per Beneficiary card Per Week - 50 transactions or USD 100,000 per Beneficiary card Per Month - 150 transactions or USD 200,000 per Beneficiary card. | P45: 0 | Q45: 0 | R45: 0 | S45: 0 | T45: USD 50,000 | U45: USD 50,000 | V45: USD 2,500 | W45: USD 50,000
A46: Belize | B46: Foreign Currency Wire Transfer (SWIFT) | C46: USD, EUR, SGD, GBP, AUD, CAD, HKD, JPY, CHF, NZD | D46: T1 | E46: B2B, B2P, P2P, P2B | F46: B2B, B2P, P2P, P2B | G46: USD, EUR, SGD, GBP, AUD, CAD, HKD, JPY, CHF, NZD | H46: Bank | I46: All SWIFT enabled banks in the country | J46: Same-day processing subject to cutoff of 07:30 UTC | K46: Remitter Name, Remitter Account Type, Remitter Identification Type, Remitter Identification Number, Remitter Address, Remitter Country Code, Beneficiary Name, Beneficiary Account Type, Beneficiary Account Number, Beneficiary Country Code, Beneficiary Address, Beneficiary City, Beneficiary Postcode, Routing Code Value 1, Routing Code Type 1 - SWIFT Code, Remit Purpose Code | L46: Remitter Beneficiary Relationship, Nature of Business, Duration of Contract, Commercial Agreement, Current Invoice | M46: Ultimate Sender Name and narrative details will be passed as part of MT103 message to beneficiary bank.Details available on beneficiary statement will be dependent on beneficiary bank. | N46: MT103 can be considered as a proof of payment and can be provided on request | O46: WIRES can be sent to all countries except for OFAC listed.MT103 can be provided on request.NIUM does not support OUR charge type for CAD currency WIRESProcessing of payments to Crimea, Donetsk, Luhansk, Sevastopol regions of Ukraine is prohibited. This list is subject to change. | P46: 0 | Q46: 0 | R46: 0 | S46: 0 | T46: No limit | U46: No limit | V46: No limit | W46: No limit
A47: Benin | B47: Foreign Currency Wire Transfer (SWIFT) | C47: USD, EUR, SGD, GBP, AUD, CAD, HKD, JPY, CHF, NZD | D47: T1 | E47: B2B, B2P, P2P, P2B | F47: B2B, B2P, P2P, P2B | G47: USD, EUR, SGD, GBP, AUD, CAD, HKD, JPY, CHF, NZD | H47: Bank | I47: All SWIFT enabled banks in the country | J47: Same-day processing subject to cutoff of 07:30 UTC | K47: Remitter Name, Remitter Account Type, Remitter Identification Type, Remitter Identification Number, Remitter Address, Remitter Country Code, Beneficiary Name, Beneficiary Account Type, Beneficiary Account Number, Beneficiary Country Code, Beneficiary Address (Recommended), Beneficiary City (Recommended), Beneficiary Postcode (Recommended), Routing Code Value 1, Routing Code Type 1 - SWIFT Code, Remit Purpose Code | L47: Remitter Beneficiary Relationship, Nature of Business, Duration of Contract, Commercial Agreement, Current Invoice | M47: Ultimate Sender Name and narrative details will be passed as part of MT103 message to beneficiary bank.Details available on beneficiary statement will be dependent on beneficiary bank. | N47: MT103 can be considered as a proof of payment and can be provided on request | O47: WIRES can be sent to all countries except for OFAC listed.MT103 can be provided on request.For foreign currency wire currencies USD, EUR, GBP - NIUM supports both OUR and SHA fee type while for other currencies AUD, CAD, CHF, JPY, NZD, HKD, SGD - NIUM supports only SHA fee typeProcessing of payments to Crimea, Donetsk, Luhansk, Sevastopol regions of Ukraine is prohibited. This list is subject to change. | P47: 0 | Q47: 0 | R47: 0 | S47: 0 | T47: No limit | U47: No limit | V47: No limit | W47: No limit
A48: Benin | B48: Local Currency Wire Transfer | C48: XOF | D48: T2 | E48: B2B, B2P, P2P, P2B | F48: B2B, B2P, P2P, P2B | G48: XOF | H48: Bank | I48: All major banks enabled with SWIFT | J48: T+2 processing subject to cutoff of 7:30 UTC | K48: Remitter Account Type, Remitter Identification Type, Remitter Identification Number, Remitter Address, Remitter Country code, Remit Purpose Code, Beneficiary Name, Beneficiary Account Number, Beneficiary Account Type, Beneficiary Country Code, Beneficiary Address, Beneficiary City, Beneficiary Postcode, Routing Code Type 1 - SWIFT, Routing Code Value 1, Remit Purpose Code, Destination Amount | L48: Remitter Beneficiary Relationship, Nature of Business, Duration of Contract, Commercial Agreement, Current Invoice | M48: Ultimate Sender Name and narrative details will be passed as part of MT103 message to beneficiary bank.Details available on beneficiary statement will be dependent on beneficiary bank. | N48: MT103 can be considered as a proof of payment and can be provided on request | O48: For WIRES, NIUM supports transactions with SHA Fee Type | P48: 0 | Q48: 0 | R48: 0 | S48: 0 | T48: No limit | U48: No limit | V48: No limit | W48: No limit
A49: Benin | B49: Visa Direct | C49: XOF | D49: Realtime | E49: B2B, B2P, P2P, P2B | F49: B2B, B2P, P2P, P2B | G49: XOF | H49: VISA | J49: 1. 24x7 Availability2. Real-time for Fast fund Enabled (Details on fast-fund enabled countries available on request)3. T+2 for other countries | K49: Remitter Name, Remitter Identification Type, Remitter Identification Number, Remitter Country Code, Beneficiary Card Number, Beneficiary Name, Beneficiary Country Code | O49: For more information, please contact your NIUM account manager team. Additional information and approval from VISA is required before this payout method can be made available.Origination of funds is allowed only from a set of countries as mentioned in the table below.In case the transaction currency does not match the destination card issuer currency, amount will be converted and credited in currency of the card issuer.In few countries, only few banks may allow the transactions.Below additional daily/monthly/yearly limits applicable for P2P transactions whichever reached first Per Day - 30 transactions or USD 10,000 per Beneficiary card Per Week - 50 transactions or USD 25,000 per Beneficiary card Per Month - 150 transactions or USD 50,000 per Beneficiary card.Below additional daily/monthly/yearly limits applicable for B2P/B2B transactions whichever reached first Per Day - 30 transactions or USD 50,000 per Beneficiary card Per Week - 50 transactions or USD 100,000 per Beneficiary card Per Month - 150 transactions or USD 200,000 per Beneficiary card. | P49: 0 | Q49: 0 | R49: 0 | S49: 0 | T49: USD 50,000 | U49: USD 50,000 | V49: USD 2,500 | W49: USD 50,000
A50: Bermuda | B50: Foreign Currency Wire Transfer (SWIFT) | C50: USD, EUR, SGD, GBP, AUD, CAD, HKD, JPY, CHF, NZD | D50: T1 | E50: B2B, B2P, P2P, P2B | F50: B2B, B2P, P2P, P2B | G50: USD, EUR, SGD, GBP, AUD, CAD, HKD, JPY, CHF, NZD | H50: Bank | I50: All SWIFT enabled banks in the country | J50: Same-day processing subject to cutoff of 07:30 UTC | K50: Remitter Name, Remitter Account Type, Remitter Identification Type, Remitter Identification Number, Remitter Address, Remitter Country Code, Beneficiary Name, Beneficiary Account Type, Beneficiary Account Number, Beneficiary Country Code, Beneficiary Address, Beneficiary City, Beneficiary Postcode, Routing Code Value 1, Routing Code Type 1 - SWIFT Code, Remit Purpose Code | L50: Remitter Beneficiary Relationship, Nature of Business, Duration of Contract, Commercial Agreement, Current Invoice | M50: Ultimate Sender Name and narrative details will be passed as part of MT103 message to beneficiary bank.Details available on beneficiary statement will be dependent on beneficiary bank. | N50: MT103 can be considered as a proof of payment and can be provided on request | O50: WIRES can be sent to all countries except for OFAC listed.MT103 can be provided on request.NIUM does not support OUR charge type for CAD currency WIRESProcessing of payments to Crimea, Donetsk, Luhansk, Sevastopol regions of Ukraine is prohibited. This list is subject to change. | P50: 0 | Q50: 0 | R50: 0 | S50: 0 | T50: No limit | U50: No limit | V50: No limit | W50: No limit
A51: Bermuda | B51: Visa Direct | C51: BMD | D51: T2 | E51: B2B, B2P, P2P, P2B | F51: B2B, B2P, P2P, P2B | G51: BMD | H51: VISA | J51: 1. 24x7 Availability2. Real-time for Fast fund Enabled (Details on fast-fund enabled countries available on request)3. T+2 for other countries | K51: Remitter Name, Remitter Identification Type, Remitter Identification Number, Remitter Country Code, Beneficiary Card Number, Beneficiary Name, Beneficiary Country Code | O51: For more information, please contact your NIUM account manager team. Additional information and approval from VISA is required before this payout method can be made available.Origination of funds is allowed only from a set of countries as mentioned in the table below.In case the transaction currency does not match the destination card issuer currency, amount will be converted and credited in currency of the card issuer.In few countries, only few banks may allow the transactions.Below additional daily/monthly/yearly limits applicable for P2P transactions whichever reached first Per Day - 30 transactions or USD 10,000 per Beneficiary card Per Week - 50 transactions or USD 25,000 per Beneficiary card Per Month - 150 transactions or USD 50,000 per Beneficiary card.Below additional daily/monthly/yearly limits applicable for B2P/B2B transactions whichever reached first Per Day - 30 transactions or USD 50,000 per Beneficiary card Per Week - 50 transactions or USD 100,000 per Beneficiary card Per Month - 150 transactions or USD 200,000 per Beneficiary card. | P51: 0 | Q51: 0 | R51: 0 | S51: 0 | T51: USD 50,000 | U51: USD 50,000 | V51: USD 2,500 | W51: USD 50,000
A52: Bhutan | B52: Foreign Currency Wire Transfer (SWIFT) | C52: USD, EUR, SGD, GBP, AUD, CAD, HKD, JPY, CHF, NZD | D52: T1 | E52: B2B, B2P, P2P, P2B | F52: B2B, B2P, P2P, P2B | G52: USD, EUR, SGD, GBP, AUD, CAD, HKD, JPY, CHF, NZD | H52: Bank | I52: All SWIFT enabled banks in the country | J52: Same-day processing subject to cutoff of 07:30 UTC | K52: Remitter Name, Remitter Account Type, Remitter Identification Type, Remitter Identification Number, Remitter Address, Remitter Country Code, Beneficiary Name, Beneficiary Account Type, Beneficiary Account Number, Beneficiary Country Code, Beneficiary Address (Recommended), Beneficiary City (Recommended), Beneficiary Postcode (Recommended), Routing Code Value 1, Routing Code Type 1 - SWIFT Code, Remit Purpose Code | L52: Remitter Beneficiary Relationship, Nature of Business, Duration of Contract, Commercial Agreement, Current Invoice | M52: Ultimate Sender Name and narrative details will be passed as part of MT103 message to beneficiary bank.Details available on beneficiary statement will be dependent on beneficiary bank. | N52: MT103 can be considered as a proof of payment and can be provided on request | O52: WIRES can be sent to all countries except for OFAC listed.MT103 can be provided on request.For foreign currency wire currencies USD, EUR, GBP - NIUM supports both OUR and SHA fee type while for other currencies AUD, CAD, CHF, JPY, NZD, HKD, SGD - NIUM supports only SHA fee typeProcessing of payments to Crimea, Donetsk, Luhansk, Sevastopol regions of Ukraine is prohibited. This list is subject to change. | P52: 0 | Q52: 0 | R52: 0 | S52: 0 | T52: No limit | U52: No limit | V52: No limit | W52: No limit
A53: Bolivia | B53: Bank Account (ACH) | C53: BOB | D53: T0 | E53: B2B, B2P, P2P, P2B | F53: B2B, B2P, P2P, P2B | G53: BOB | H53: Partner | I53: All major banks enabled in Bolivia | J53: Same-day credit subject to cutoff of 16:45 local time | K53: Remitter Name, Remitter Account Type, Remitter Identification Type, Remitter Identification Number, Remitter Address, Remitter Country Code, Remitter State, Remit Purpose Code, Beneficiary Name, Beneficiary Account Number, Beneficiary Account Type, Beneficiary Country Code, Beneficiary Address, Beneficiary City, Beneficiary Postcode, Routing Code Type 1 â€“ SWIFT CODE, Routing Code Value, Remit Purpose Code, Remitter DOB, Beneficiary Contact Number, Beneficiary Identification Type, Beneficiary Identification Value, Beneficiary Bank Account Type | L53: Remitter Beneficiary Relationship, Nature of Business, Duration of Contract, Commercial Agreement, Current Invoice | M53: Domestic Clearing System limits ability to transfer full remitter information to the Beneficiary.Visibility of Standard Statement Narration is missing. | O53: The Remitter State field is mandatory only for remitters located in the US or Canada. | P53: USD 1 | Q53: USD 1 | R53: USD 1 | S53: USD 1 | T53: USD 100,000 | U53: USD 25,000 | V53: USD 25,000 | W53: USD 25,000
A54: Bolivia | B54: Foreign Currency Wire Transfer (SWIFT) | C54: USD, EUR, SGD, GBP, AUD, CAD, HKD, JPY, CHF, NZD | D54: T1 | E54: B2B, B2P, P2P, P2B | F54: B2B, B2P, P2P, P2B | G54: USD, EUR, SGD, GBP, AUD, CAD, HKD, JPY, CHF, NZD | H54: Bank | I54: All SWIFT enabled banks in the country | J54: Same-day processing subject to cutoff of 07:30 UTC | K54: Remitter Name, Remitter Account Type, Remitter Identification Type, Remitter Identification Number, Remitter Address, Remitter Country Code, Beneficiary Name, Beneficiary Account Type, Beneficiary Account Number, Beneficiary Country Code, Beneficiary Address, Beneficiary City, Beneficiary Postcode, Routing Code Value 1, Routing Code Type 1 - SWIFT Code, Remit Purpose Code | L54: Remitter Beneficiary Relationship, Nature of Business, Duration of Contract, Commercial Agreement, Current Invoice | M54: Ultimate Sender Name and narrative details will be passed as part of MT103 message to beneficiary bank.Details available on beneficiary statement will be dependent on beneficiary bank. | N54: MT103 can be considered as a proof of payment and can be provided on request | O54: WIRES can be sent to all countries except for OFAC listed.MT103 can be provided on request.NIUM does not support OUR charge type for CAD currency WIRESProcessing of payments to Crimea, Donetsk, Luhansk, Sevastopol regions of Ukraine is prohibited. This list is subject to change. | P54: 0 | Q54: 0 | R54: 0 | S54: 0 | T54: No limit | U54: No limit | V54: No limit | W54: No limit
A55: Bosnia and Herzegovina | B55: Foreign Currency Wire Transfer (SWIFT) | C55: USD, EUR, SGD, GBP, AUD, CAD, HKD, JPY, CHF, NZD | D55: T1 | E55: B2B, B2P, P2P, P2B | F55: B2B, B2P, P2P, P2B | G55: USD, EUR, SGD, GBP, AUD, CAD, HKD, JPY, CHF, NZD | H55: Bank | I55: All SWIFT enabled banks in the country | J55: Same-day processing subject to cutoff of 07:30 UTC | K55: Remitter Name, Remitter Account Type, Remitter Identification Type, Remitter Identification Number, Remitter Address, Remitter Country Code, Beneficiary Name, Beneficiary Account Type, Beneficiary Account Number, Beneficiary Country Code, Beneficiary Address, Beneficiary City, Beneficiary Postcode, Routing Code Value 1, Routing Code Type 1 - SWIFT Code, Remit Purpose Code | L55: Remitter Beneficiary Relationship, Nature of Business, Duration of Contract, Commercial Agreement, Current Invoice | M55: Ultimate Sender Name and narrative details will be passed as part of MT103 message to beneficiary bank.Details available on beneficiary statement will be dependent on beneficiary bank. | N55: MT103 can be considered as a proof of payment and can be provided on request | O55: WIRES can be sent to all countries except for OFAC listed.MT103 can be provided on request.NIUM does not support OUR charge type for CAD currency WIRESProcessing of payments to Crimea, Donetsk, Luhansk, Sevastopol regions of Ukraine is prohibited. This list is subject to change. | P55: 0 | Q55: 0 | R55: 0 | S55: 0 | T55: No limit | U55: No limit | V55: No limit | W55: No limit
A56: Botswana | B56: Foreign Currency Wire Transfer (SWIFT) | C56: USD, EUR, SGD, GBP, AUD, CAD, HKD, JPY, CHF, NZD | D56: T1 | E56: B2B, B2P, P2P, P2B | F56: B2B, B2P, P2P, P2B | G56: USD, EUR, SGD, GBP, AUD, CAD, HKD, JPY, CHF, NZD | H56: Bank | I56: All SWIFT enabled banks in the country | J56: Same-day processing subject to cutoff of 07:30 UTC | K56: Remitter Name, Remitter Account Type, Remitter Identification Type, Remitter Identification Number, Remitter Address, Remitter Country Code, Beneficiary Name, Beneficiary Account Type, Beneficiary Account Number, Beneficiary Country Code, Beneficiary Address, Beneficiary City, Beneficiary Postcode, Routing Code Value 1, Routing Code Type 1 - SWIFT Code, Remit Purpose Code | L56: Remitter Beneficiary Relationship, Nature of Business, Duration of Contract, Commercial Agreement, Current Invoice | M56: Ultimate Sender Name and narrative details will be passed as part of MT103 message to beneficiary bank.Details available on beneficiary statement will be dependent on beneficiary bank. | N56: MT103 can be considered as a proof of payment and can be provided on request | O56: WIRES can be sent to all countries except for OFAC listed.MT103 can be provided on request.NIUM does not support OUR charge type for CAD currency WIRESProcessing of payments to Crimea, Donetsk, Luhansk, Sevastopol regions of Ukraine is prohibited. This list is subject to change. | P56: 0 | Q56: 0 | R56: 0 | S56: 0 | T56: No limit | U56: No limit | V56: No limit | W56: No limit
A57: Botswana | B57: Visa Direct | C57: BWP | D57: Realtime | E57: B2B, B2P, P2P, P2B | F57: B2B, B2P, P2P, P2B | G57: BWP | H57: VISA | J57: 1. 24x7 Availability2. Real-time for Fast fund Enabled (Details on fast-fund enabled countries available on request)3. T+2 for other countries | K57: Remitter Name, Remitter Identification Type, Remitter Identification Number, Remitter Country Code, Beneficiary Card Number, Beneficiary Name, Beneficiary Country Code | O57: For more information, please contact your NIUM account manager team. Additional information and approval from VISA is required before this payout method can be made available.Origination of funds is allowed only from a set of countries as mentioned in the table below.In case the transaction currency does not match the destination card issuer currency, amount will be converted and credited in currency of the card issuer.In few countries, only few banks may allow the transactions.Below additional daily/monthly/yearly limits applicable for P2P transactions whichever reached first Per Day - 30 transactions or USD 10,000 per Beneficiary card Per Week - 50 transactions or USD 25,000 per Beneficiary card Per Month - 150 transactions or USD 50,000 per Beneficiary card.Below additional daily/monthly/yearly limits applicable for B2P/B2B transactions whichever reached first Per Day - 30 transactions or USD 50,000 per Beneficiary card Per Week - 50 transactions or USD 100,000 per Beneficiary card Per Month - 150 transactions or USD 200,000 per Beneficiary card. | P57: 0 | Q57: 0 | R57: 0 | S57: 0 | T57: USD 50,000 | U57: USD 50,000 | V57: USD 2,500 | W57: USD 50,000
A58: Bouvet Island | B58: Foreign Currency Wire Transfer (SWIFT) | C58: USD, EUR, SGD, GBP, AUD, CAD, HKD, JPY, CHF, NZD | D58: T1 | E58: B2B, B2P, P2P, P2B | F58: B2B, B2P, P2P, P2B | G58: USD, EUR, SGD, GBP, AUD, CAD, HKD, JPY, CHF, NZD | H58: Bank | I58: All SWIFT enabled banks in the country | J58: Same-day processing subject to cutoff of 07:30 UTC | K58: Remitter Name, Remitter Account Type, Remitter Identification Type, Remitter Identification Number, Remitter Address, Remitter Country Code, Beneficiary Name, Beneficiary Account Type, Beneficiary Account Number, Beneficiary Country Code, Beneficiary Address, Beneficiary City, Beneficiary Postcode, Routing Code Value 1, Routing Code Type 1 - SWIFT Code, Remit Purpose Code | L58: Remitter Beneficiary Relationship, Nature of Business, Duration of Contract, Commercial Agreement, Current Invoice | M58: Ultimate Sender Name and narrative details will be passed as part of MT103 message to beneficiary bank.Details available on beneficiary statement will be dependent on beneficiary bank. | N58: MT103 can be considered as a proof of payment and can be provided on request | O58: WIRES can be sent to all countries except for OFAC listed.MT103 can be provided on request.NIUM does not support OUR charge type for CAD currency WIRESProcessing of payments to Crimea, Donetsk, Luhansk, Sevastopol regions of Ukraine is prohibited. This list is subject to change. | P58: 0 | Q58: 0 | R58: 0 | S58: 0 | T58: No limit | U58: No limit | V58: No limit | W58: No limit
A59: Brazil | B59: Bank Account (ACH) | C59: BRL | D59: Realtime | E59: B2B, B2P, P2P, P2B | F59: B2B, B2P, P2P, P2B | G59: BRL | H59: Bank | I59: All banks in BR | J59: Realtime, 24x7 availability | K59: Remitter Name, Remitter Account Type, Remitter Identification Type, Remitter Identification Number, Remitter Address, Remitter Country Code, Beneficiary Account Type, Beneficiary Bank Account Type, Beneficiary Account Number, Beneficiary Identification Type, Remit Purpose Code, Beneficiary Contact Number, Routing Code Value 1, Beneficiary Bank Code / SWIFT CODE, Beneficiary Country Code, Beneficiary Identification Value, Routing Code Type 1 - Branch Code | L59: Remitter Beneficiary Relationship, Nature of Business, Duration of Contract, Commercial Agreement, Current Invoice | M59: Domestic Clearing System limits ability to transfer full remitter information to the Beneficiary. Visibility of Standard Statement Narration is missing | N59: Upon request, Proof of Payment for a transaction can be made available. | P59: BRL 0.06 | Q59: BRL 0.06 | R59: BRL 0.06 | S59: BRL 0.06 | T59: No limit | U59: No limit | V59: No limit | W59: No limit
A60: Brazil | B60: Foreign Currency Wire Transfer (SWIFT) | C60: USD, EUR, SGD, GBP, AUD, CAD, HKD, JPY, CHF, NZD | D60: T1 | E60: B2B, B2P, P2P, P2B | F60: B2B, B2P, P2P, P2B | G60: USD, EUR, SGD, GBP, AUD, CAD, HKD, JPY, CHF, NZD | H60: Bank | I60: All SWIFT enabled banks in the country | J60: Same-day processing subject to cutoff of 07:30 UTC | K60: Remitter Name, Remitter Account Type, Remitter Identification Type, Remitter Identification Number, Remitter Address, Remitter Country Code, Beneficiary Name, Beneficiary Account Type, Beneficiary Account Number, Beneficiary Country Code, Beneficiary Address, Beneficiary City, Beneficiary Postcode, Routing Code Value 1, Routing Code Type 1 - SWIFT Code, Remit Purpose Code | L60: Remitter Beneficiary Relationship, Nature of Business, Duration of Contract, Commercial Agreement, Current Invoice | M60: Ultimate Sender Name and narrative details will be passed as part of MT103 message to beneficiary bank.Details available on beneficiary statement will be dependent on beneficiary bank. | N60: MT103 can be considered as a proof of payment and can be provided on request | O60: WIRES can be sent to all countries except for OFAC listed.MT103 can be provided on request.NIUM does not support OUR charge type for CAD currency WIRESProcessing of payments to Crimea, Donetsk, Luhansk, Sevastopol regions of Ukraine is prohibited. This list is subject to change. | P60: 0 | Q60: 0 | R60: 0 | S60: 0 | T60: No limit | U60: No limit | V60: No limit | W60: No limit
A61: Brazil | B61: Proxy (PIX) | C61: BRL | D61: Realtime | E61: B2B, B2P, P2P | F61: B2B, B2P, P2P | G61: BRL | H61: Bank | I61: All major banks in Brazil. List Available | J61: Real Time, 24x7 | K61: Remitter Name, Remitter Identification Type, Remitter Country Code, Beneficiary Name, Remit Purpose Code, Proxy Value*, Remitter Account Type, Remitter Identification Number, Remitter Address, Beneficiary Country Code, Proxy Type, Beneficiary Identification Type | L61: Remitter Beneficiary Relationship, Nature of Business, Duration of Contract, Commercial Agreement, Current Invoice | M61: Domestic Clearing System limits ability to transfer full remitter information to the Beneficiary. Visibility of Standard Statement Narration is missing. | O61: 1. Value for proxy type should be a. MOBILE b. EMAIL c. ID d. RANDOM KEY3. There can be additional transaction Limits set up by Beneficiary Banks for PIX payouts.4. Supporting Documents will be asked from beneficiary by their banks basis the amount threshold crossed.5. Details of the thresholds and docs required available and can be shared upon request. | P61: BRL 0.06 | Q61: BRL 0.06 | R61: BRL 0.06 | S61: Not Supported | T61: No limit | U61: No limit | V61: No limit | W61: Not Supported
A62: British Virgin Islands | B62: Foreign Currency Wire Transfer (SWIFT) | C62: USD, EUR, SGD, GBP, AUD, CAD, HKD, JPY, CHF, NZD | D62: T1 | E62: B2B, B2P, P2P, P2B | F62: B2B, B2P, P2P, P2B | G62: USD, EUR, SGD, GBP, AUD, CAD, HKD, JPY, CHF, NZD | H62: Bank | I62: All SWIFT enabled banks in the country | J62: Same-day processing subject to cutoff of 07:30 UTC | K62: Remitter Name, Remitter Account Type, Remitter Identification Type, Remitter Identification Number, Remitter Address, Remitter Country Code, Beneficiary Name, Beneficiary Account Type, Beneficiary Account Number, Beneficiary Country Code, Beneficiary Address, Beneficiary City, Beneficiary Postcode, Routing Code Value 1, Routing Code Type 1 - SWIFT Code, Remit Purpose Code | L62: Remitter Beneficiary Relationship, Nature of Business, Duration of Contract, Commercial Agreement, Current Invoice | M62: Ultimate Sender Name and narrative details will be passed as part of MT103 message to beneficiary bank.Details available on beneficiary statement will be dependent on beneficiary bank. | N62: MT103 can be considered as a proof of payment and can be provided on request | O62: WIRES can be sent to all countries except for OFAC listed.MT103 can be provided on request.NIUM does not support OUR charge type for CAD currency WIRESProcessing of payments to Crimea, Donetsk, Luhansk, Sevastopol regions of Ukraine is prohibited. This list is subject to change. | P62: 0 | Q62: 0 | R62: 0 | S62: 0 | T62: No limit | U62: No limit | V62: No limit | W62: No limit
A63: Brunei | B63: Foreign Currency Wire Transfer (SWIFT) | C63: USD, EUR, SGD, GBP, AUD, CAD, HKD, JPY, CHF, NZD | D63: T1 | E63: B2B, B2P, P2P, P2B | F63: B2B, B2P, P2P, P2B | G63: USD, EUR, SGD, GBP, AUD, CAD, HKD, JPY, CHF, NZD | H63: Bank | I63: All SWIFT enabled banks in the country | J63: Same-day processing subject to cutoff of 07:30 UTC | K63: Remitter Name, Remitter Account Type, Remitter Identification Type, Remitter Identification Number, Remitter Address, Remitter Country Code, Beneficiary Name, Beneficiary Account Type, Beneficiary Account Number, Beneficiary Country Code, Beneficiary Address (Recommended), Beneficiary City (Recommended), Beneficiary Postcode (Recommended), Routing Code Value 1, Routing Code Type 1 - SWIFT Code, Remit Purpose Code | L63: Remitter Beneficiary Relationship, Nature of Business, Duration of Contract, Commercial Agreement, Current Invoice | M63: Ultimate Sender Name and narrative details will be passed as part of MT103 message to beneficiary bank.Details available on beneficiary statement will be dependent on beneficiary bank. | N63: MT103 can be considered as a proof of payment and can be provided on request | O63: WIRES can be sent to all countries except for OFAC listed.MT103 can be provided on request.For foreign currency wire currencies USD, EUR, GBP - NIUM supports both OUR and SHA fee type while for other currencies AUD, CAD, CHF, JPY, NZD, HKD, SGD - NIUM supports only SHA fee typeProcessing of payments to Crimea, Donetsk, Luhansk, Sevastopol regions of Ukraine is prohibited. This list is subject to change. | P63: 0 | Q63: 0 | R63: 0 | S63: 0 | T63: No limit | U63: No limit | V63: No limit | W63: No limit
A64: Brunei | B64: Visa Direct | C64: BND | D64: T2 | E64: B2B, B2P, P2P, P2B | F64: B2B, B2P, P2P, P2B | G64: BND | H64: VISA | J64: 1. 24x7 Availability2. Real-time for Fast fund Enabled (Details on fast-fund enabled countries available on request)3. T+2 for other countries | K64: Remitter Name, Remitter Identification Type, Remitter Identification Number, Remitter Country Code, Beneficiary Card Number, Beneficiary Name, Beneficiary Country Code | O64: For more information, please contact your NIUM account manager team. Additional information and approval from VISA is required before this payout method can be made available.Origination of funds is allowed only from a set of countries as mentioned in the table below.In case the transaction currency does not match the destination card issuer currency, amount will be converted and credited in currency of the card issuer.In few countries, only few banks may allow the transactions.Below additional daily/monthly/yearly limits applicable for P2P transactions whichever reached first Per Day - 30 transactions or USD 10,000 per Beneficiary card Per Week - 50 transactions or USD 25,000 per Beneficiary card Per Month - 150 transactions or USD 50,000 per Beneficiary card.Below additional daily/monthly/yearly limits applicable for B2P/B2B transactions whichever reached first Per Day - 30 transactions or USD 50,000 per Beneficiary card Per Week - 50 transactions or USD 100,000 per Beneficiary card Per Month - 150 transactions or USD 200,000 per Beneficiary card. | P64: 0 | Q64: 0 | R64: 0 | S64: 0 | T64: USD 50,000 | U64: USD 50,000 | V64: USD 2,500 | W64: USD 50,000
A65: Bulgaria | B65: Bank Account (SEPA) | C65: EUR | D65: Realtime | E65: B2B, B2P, P2P, P2B | F65: B2B, B2P, P2P, P2B | G65: EUR | H65: Bank | I65: All banks connected with SEPA Network | J65: 1. Real-time for transaction amount <= EUR 100,0002. Same-day for transaction amount > EUR 100,000 subject to cutoff of 14.00 EET | K65: Remitter Name, Remitter Account Type, Remitter Address, Remitter Country Code, Remitter Identification Type, Remitter Identification Number, Remit Purpose Code, Remitter City, Remitter Postcode, Beneficiary Name, Beneficiary Country Code, Beneficiary Account Type, Beneficiary Account Number - IBAN, Routing Code Type 1 - SWIFT CODE, Routing Code Value 1 | L65: Remitter Beneficiary Relationship, Nature of Business, Duration of Contract, Commercial Agreement, Current Invoice | M65: Remitter Name & NIUM appears in the beneficiary statement | N65: Upon request, Proof of Payment for a transaction can be made available. | O65: 1. Coverage includes the EU as well as several Non-EU countries.2. Not all supported countries support Realtime payments3. Few banks in Instant supported countries may not support instant payments and payments will be routed through Standard mode in such cases.4.Certain banks require the complete 11-character SWIFT codeâ€”including the branch identifierâ€”in order to accurately route and successfully process the payment. | P65: EUR 0.01 | Q65: EUR 0.01 | R65: EUR 0.01 | S65: EUR 0.01 | T65: No limit | U65: No limit | V65: No limit | W65: No limit
A66: Bulgaria | B66: Foreign Currency Wire Transfer (SWIFT) | C66: USD, EUR, SGD, GBP, AUD, CAD, HKD, JPY, CHF, NZD | D66: T1 | E66: B2B, B2P, P2P, P2B | F66: B2B, B2P, P2P, P2B | G66: USD, EUR, SGD, GBP, AUD, CAD, HKD, JPY, CHF, NZD | H66: Bank | I66: All SWIFT enabled banks in the country | J66: Same-day processing subject to cutoff of 07:30 UTC | K66: Remitter Name, Remitter Account Type, Remitter Identification Type, Remitter Identification Number, Remitter Address, Remitter Country Code, Beneficiary Name, Beneficiary Account Type, Beneficiary Account Number, Beneficiary Country Code, Beneficiary Address (Recommended), Beneficiary City (Recommended), Beneficiary Postcode (Recommended), Routing Code Value 1, Routing Code Type 1 - SWIFT Code, Remit Purpose Code | L66: Remitter Beneficiary Relationship, Nature of Business, Duration of Contract, Commercial Agreement, Current Invoice | M66: Ultimate Sender Name and narrative details will be passed as part of MT103 message to beneficiary bank.Details available on beneficiary statement will be dependent on beneficiary bank. | N66: MT103 can be considered as a proof of payment and can be provided on request | O66: WIRES can be sent to all countries except for OFAC listed.MT103 can be provided on request.For foreign currency wire currencies USD, EUR, GBP - NIUM supports both OUR and SHA fee type while for other currencies AUD, CAD, CHF, JPY, NZD, HKD, SGD - NIUM supports only SHA fee typeProcessing of payments to Crimea, Donetsk, Luhansk, Sevastopol regions of Ukraine is prohibited. This list is subject to change. | P66: 0 | Q66: 0 | R66: 0 | S66: 0 | T66: No limit | U66: No limit | V66: No limit | W66: No limit
A67: Bulgaria | B67: Visa Direct | C67: BGN | D67: Realtime | E67: B2B, B2P, P2P, P2B | F67: B2B, B2P, P2P, P2B | G67: BGN | H67: VISA | J67: 1. 24x7 Availability2. Real-time for Fast fund Enabled (Details on fast-fund enabled countries available on request)3. T+2 for other countries | K67: Remitter Name, Remitter Identification Type, Remitter Identification Number, Remitter Country Code, Beneficiary Card Number, Beneficiary Name, Beneficiary Country Code | O67: For more information, please contact your NIUM account manager team. Additional information and approval from VISA is required before this payout method can be made available.Origination of funds is allowed only from a set of countries as mentioned in the table below.In case the transaction currency does not match the destination card issuer currency, amount will be converted and credited in currency of the card issuer.In few countries, only few banks may allow the transactions.Below additional daily/monthly/yearly limits applicable for P2P transactions whichever reached first Per Day - 30 transactions or USD 10,000 per Beneficiary card Per Week - 50 transactions or USD 25,000 per Beneficiary card Per Month - 150 transactions or USD 50,000 per Beneficiary card.Below additional daily/monthly/yearly limits applicable for B2P/B2B transactions whichever reached first Per Day - 30 transactions or USD 50,000 per Beneficiary card Per Week - 50 transactions or USD 100,000 per Beneficiary card Per Month - 150 transactions or USD 200,000 per Beneficiary card. | P67: 0 | Q67: 0 | R67: 0 | S67: 0 | T67: USD 50,000 | U67: USD 50,000 | V67: USD 2,500 | W67: USD 50,000
A68: Burkina Faso | B68: Foreign Currency Wire Transfer (SWIFT) | C68: USD, EUR, SGD, GBP, AUD, CAD, HKD, JPY, CHF, NZD | D68: T1 | E68: B2B, B2P, P2P, P2B | F68: B2B, B2P, P2P, P2B | G68: USD, EUR, SGD, GBP, AUD, CAD, HKD, JPY, CHF, NZD | H68: Bank | I68: All SWIFT enabled banks in the country | J68: Same-day processing subject to cutoff of 07:30 UTC | K68: Remitter Name, Remitter Account Type, Remitter Identification Type, Remitter Identification Number, Remitter Address, Remitter Country Code, Beneficiary Name, Beneficiary Account Type, Beneficiary Account Number, Beneficiary Country Code, Beneficiary Address, Beneficiary City, Beneficiary Postcode, Routing Code Value 1, Routing Code Type 1 - SWIFT Code, Remit Purpose Code | L68: Remitter Beneficiary Relationship, Nature of Business, Duration of Contract, Commercial Agreement, Current Invoice | M68: Ultimate Sender Name and narrative details will be passed as part of MT103 message to beneficiary bank.Details available on beneficiary statement will be dependent on beneficiary bank. | N68: MT103 can be considered as a proof of payment and can be provided on request | O68: WIRES can be sent to all countries except for OFAC listed.MT103 can be provided on request.NIUM does not support OUR charge type for CAD currency WIRESProcessing of payments to Crimea, Donetsk, Luhansk, Sevastopol regions of Ukraine is prohibited. This list is subject to change. | P68: 0 | Q68: 0 | R68: 0 | S68: 0 | T68: No limit | U68: No limit | V68: No limit | W68: No limit
A69: Burkina Faso | B69: Local Currency Wire Transfer | C69: XOF | D69: T2 | E69: B2B, B2P, P2P, P2B | F69: B2B, B2P, P2P, P2B | G69: XOF | H69: Bank | I69: All major banks enabled with SWIFT | J69: T+2 processing subject to cutoff of 7:30 UTC | K69: Remitter Account Type, Remitter Identification Type, Remitter Identification Number, Remitter Address, Remitter Country code, Remit Purpose Code, Beneficiary Name, Beneficiary Account Number, Beneficiary Account Type, Beneficiary Country Code, Beneficiary Address, Beneficiary City, Beneficiary Postcode, Routing Code Type 1 - SWIFT, Routing Code Value 1, Remit Purpose Code, Destination Amount | L69: Remitter Beneficiary Relationship, Nature of Business, Duration of Contract, Commercial Agreement, Current Invoice | M69: Ultimate Sender Name and narrative details will be passed as part of MT103 message to beneficiary bank.Details available on beneficiary statement will be dependent on beneficiary bank. | N69: MT103 can be considered as a proof of payment and can be provided on request | O69: For WIRES, NIUM supports transactions with SHA Fee Type | P69: 0 | Q69: 0 | R69: 0 | S69: 0 | T69: No limit | U69: No limit | V69: No limit | W69: No limit
A70: Burkina Faso | B70: Visa Direct | C70: XOF | D70: Realtime | E70: B2B, B2P, P2P, P2B | F70: B2B, B2P, P2P, P2B | G70: XOF | H70: VISA | J70: 1. 24x7 Availability2. Real-time for Fast fund Enabled (Details on fast-fund enabled countries available on request)3. T+2 for other countries | K70: Remitter Name, Remitter Identification Type, Remitter Identification Number, Remitter Country Code, Beneficiary Card Number, Beneficiary Name, Beneficiary Country Code | O70: For more information, please contact your NIUM account manager team. Additional information and approval from VISA is required before this payout method can be made available.Origination of funds is allowed only from a set of countries as mentioned in the table below.In case the transaction currency does not match the destination card issuer currency, amount will be converted and credited in currency of the card issuer.In few countries, only few banks may allow the transactions.Below additional daily/monthly/yearly limits applicable for P2P transactions whichever reached first Per Day - 30 transactions or USD 10,000 per Beneficiary card Per Week - 50 transactions or USD 25,000 per Beneficiary card Per Month - 150 transactions or USD 50,000 per Beneficiary card.Below additional daily/monthly/yearly limits applicable for B2P/B2B transactions whichever reached first Per Day - 30 transactions or USD 50,000 per Beneficiary card Per Week - 50 transactions or USD 100,000 per Beneficiary card Per Month - 150 transactions or USD 200,000 per Beneficiary card. | P70: 0 | Q70: 0 | R70: 0 | S70: 0 | T70: USD 50,000 | U70: USD 50,000 | V70: USD 2,500 | W70: USD 50,000
A71: Cambodia | B71: Foreign Currency Wire Transfer (SWIFT) | C71: USD, EUR, SGD, GBP, AUD, CAD, HKD, JPY, CHF, NZD | D71: T1 | E71: B2B, B2P, P2P, P2B | F71: B2B, B2P, P2P, P2B | G71: USD, EUR, SGD, GBP, AUD, CAD, HKD, JPY, CHF, NZD | H71: Bank | I71: All SWIFT enabled banks in the country | J71: Same-day processing subject to cutoff of 07:30 UTC | K71: Remitter Name, Remitter Account Type, Remitter Identification Type, Remitter Identification Number, Remitter Address, Remitter Country Code, Beneficiary Name, Beneficiary Account Type, Beneficiary Account Number, Beneficiary Country Code, Beneficiary Address, Beneficiary City, Beneficiary Postcode, Routing Code Value 1, Routing Code Type 1 - SWIFT Code, Remit Purpose Code | L71: Remitter Beneficiary Relationship, Nature of Business, Duration of Contract, Commercial Agreement, Current Invoice | M71: Ultimate Sender Name and narrative details will be passed as part of MT103 message to beneficiary bank.Details available on beneficiary statement will be dependent on beneficiary bank. | N71: MT103 can be considered as a proof of payment and can be provided on request | O71: WIRES can be sent to all countries except for OFAC listed.MT103 can be provided on request.NIUM does not support OUR charge type for CAD currency WIRESProcessing of payments to Crimea, Donetsk, Luhansk, Sevastopol regions of Ukraine is prohibited. This list is subject to change. | P71: 0 | Q71: 0 | R71: 0 | S71: 0 | T71: No limit | U71: No limit | V71: No limit | W71: No limit
A72: Cambodia | B72: Visa Direct | C72: KHR | D72: Realtime | E72: B2B, B2P, P2P, P2B | F72: B2B, B2P, P2P, P2B | G72: KHR | H72: VISA | J72: 1. 24x7 Availability2. Real-time for Fast fund Enabled (Details on fast-fund enabled countries available on request)3. T+2 for other countries | K72: Remitter Name, Remitter Identification Type, Remitter Identification Number, Remitter Country Code, Beneficiary Card Number, Beneficiary Name, Beneficiary Country Code | O72: For more information, please contact your NIUM account manager team. Additional information and approval from VISA is required before this payout method can be made available.Origination of funds is allowed only from a set of countries as mentioned in the table below.In case the transaction currency does not match the destination card issuer currency, amount will be converted and credited in currency of the card issuer.In few countries, only few banks may allow the transactions.Below additional daily/monthly/yearly limits applicable for P2P transactions whichever reached first Per Day - 30 transactions or USD 10,000 per Beneficiary card Per Week - 50 transactions or USD 25,000 per Beneficiary card Per Month - 150 transactions or USD 50,000 per Beneficiary card.Below additional daily/monthly/yearly limits applicable for B2P/B2B transactions whichever reached first Per Day - 30 transactions or USD 50,000 per Beneficiary card Per Week - 50 transactions or USD 100,000 per Beneficiary card Per Month - 150 transactions or USD 200,000 per Beneficiary card. | P72: 0 | Q72: 0 | R72: 0 | S72: 0 | T72: USD 50,000 | U72: USD 50,000 | V72: USD 2,500 | W72: USD 50,000
A73: Cameroon | B73: Foreign Currency Wire Transfer (SWIFT) | C73: USD, EUR, SGD, GBP, AUD, CAD, HKD, JPY, CHF, NZD | D73: T1 | E73: B2B, B2P, P2P, P2B | F73: B2B, B2P, P2P, P2B | G73: USD, EUR, SGD, GBP, AUD, CAD, HKD, JPY, CHF, NZD | H73: Bank | I73: All SWIFT enabled banks in the country | J73: Same-day processing subject to cutoff of 07:30 UTC | K73: Remitter Name, Remitter Account Type, Remitter Identification Type, Remitter Identification Number, Remitter Address, Remitter Country Code, Beneficiary Name, Beneficiary Account Type, Beneficiary Account Number, Beneficiary Country Code, Beneficiary Address, Beneficiary City, Beneficiary Postcode, Routing Code Value 1, Routing Code Type 1 - SWIFT Code, Remit Purpose Code | L73: Remitter Beneficiary Relationship, Nature of Business, Duration of Contract, Commercial Agreement, Current Invoice | M73: Ultimate Sender Name and narrative details will be passed as part of MT103 message to beneficiary bank.Details available on beneficiary statement will be dependent on beneficiary bank. | N73: MT103 can be considered as a proof of payment and can be provided on request | O73: WIRES can be sent to all countries except for OFAC listed.MT103 can be provided on request.NIUM does not support OUR charge type for CAD currency WIRESProcessing of payments to Crimea, Donetsk, Luhansk, Sevastopol regions of Ukraine is prohibited. This list is subject to change. | P73: 0 | Q73: 0 | R73: 0 | S73: 0 | T73: No limit | U73: No limit | V73: No limit | W73: No limit
A74: Canada | B74: Bank Account (ACH) | C74: CAD | D74: T1 | E74: B2B, B2P, P2P, P2B | F74: B2B, B2P, P2P, P2B | G74: CAD | H74: Bank | I74: All banks in Canada | J74: T+1 day credit subject to cutoff of 18:00 ET | K74: Remitter Name, Remitter Account Type, Remitter Identification Type, Remitter Identification Number, Remitter Address, Remitter Country Code, Remitter City, Remitter Post Code, Beneficiary Name, Beneficiary Account Type, Beneficiary Account Number, Beneficiary Country Code, Beneficiary Address (Recommended), Beneficiary City (Recommended), Beneficiary Postcode (Recommended), Beneficiary Bank Code/SWIFT Code, Routing Code Type 1 - Transit Code, Routing Code Value 1 | L74: Remitter Beneficiary Relationship, Nature of Business, Duration of Contract, Commercial Agreement, Current Invoice | M74: Domestic Clearing System limits ability to transfer full remitter information to the Beneficiary. Visibility of Standard Statement Narration is missing. | O74: *The status update will be done on T+1 basis though the Beneficiary may receive the credit before this. | P74: 0 | Q74: CAD 0.01 | R74: 0 | S74: 0 | T74: CAD 99,000,000 | U74: CAD 99,000,000 | V74: CAD 99,000,000 | W74: CAD 99,000,000
A75: Canada | B75: Bank Account (ACH) | C75: USD | D75: T1 | E75: B2B, B2P, P2P, P2B | F75: B2B, B2P, P2P, P2B | G75: USD | H75: Bank | I75: All banks in Canada | J75: T+1 day credit subject to cutoff of 23:59 ET | K75: Remitter Name, Remitter Account Type, Remitter Identification Type, Remitter Identificiation Number, Remitter Address, Remitter Country Code, Remitter City, Remitter Postcode, Beneficiary Name, Beneficiary Account Number, Beneficiary Account Type, Beneficiary Country Code, Beneficiary Address (Recommended), Beneficiary City (Recommended), Beneficiary Postcode (Recommended), Beneficiary Bank Code/SWIFT Code, Routing Code Type 1 - Transit Code, Routing Code Value 1 | L75: Remitter Beneficiary Relationship, Nature of Business, Duration of Contract, Commercial Agreement, Current Invoice | M75: Domestic Clearing System limits ability to transfer full remitter information to the Beneficiary. Visibility of Standard Statement Narration is missing. | O75: *The status update will be done on T+1 basis though the Beneficiary may receive the credit before this. | P75: USD 0.01 | Q75: USD 0.01 | R75: USD 0.01 | S75: USD 0.01 | T75: USD 99,000,000 | U75: USD 99,000,000 | V75: USD 99,000,000 | W75: USD 99,000,000
A76: Canada | B76: Foreign Currency Wire Transfer (SWIFT) | C76: USD, EUR, SGD, GBP, AUD, CAD, HKD, JPY, CHF, NZD | D76: T1 | E76: B2B, B2P, P2P, P2B | F76: B2B, B2P, P2P, P2B | G76: USD, EUR, SGD, GBP, AUD, CAD, HKD, JPY, CHF, NZD | H76: Bank | I76: All SWIFT enabled banks in the country | J76: Same-day processing subject to cutoff of 07:30 UTC | K76: Remitter Name, Remitter Account Type, Remitter Identification Type, Remitter Identification Number, Remitter Address, Remitter Country Code, Beneficiary Name, Beneficiary Account Type, Beneficiary Account Number, Beneficiary Country Code, Beneficiary Address, Beneficiary City, Beneficiary Postcode, Routing Code Value 1, Routing Code Type 1 - SWIFT Code, Remit Purpose Code | L76: Remitter Beneficiary Relationship, Nature of Business, Duration of Contract, Commercial Agreement, Current Invoice | M76: Ultimate Sender Name and narrative details will be passed as part of MT103 message to beneficiary bank.Details available on beneficiary statement will be dependent on beneficiary bank. | N76: MT103 can be considered as a proof of payment and can be provided on request | O76: WIRES can be sent to all countries except for OFAC listed.MT103 can be provided on request.NIUM does not support OUR charge type for CAD currency WIRESProcessing of payments to Crimea, Donetsk, Luhansk, Sevastopol regions of Ukraine is prohibited. This list is subject to change. | P76: 0 | Q76: 0 | R76: 0 | S76: 0 | T76: No limit | U76: No limit | V76: No limit | W76: No limit
A77: Canada | B77: Interac | C77: CAD | D77: Realtime | E77: B2B, B2P, P2P, P2B | F77: B2B, B2P, P2P, P2B | G77: CAD | H77: Bank | I77: All Interac supported banks in Canada | J77: Near real time(upto 60 mins) - subject to window of 05:00hrs ET to 22:30hrs ET | K77: Remitter Name, Remitter Account Type, Remitter Identification Type, Remitter Identification Number, Remitter Address, Remitter Country Code, Remitter City, Remitter Post Code, Beneficiary Name, Beneficiary Account Type, Beneficiary Account Number, Beneficiary Country Code, Beneficiary Address, Beneficiary City, Beneficiary Postcode, Beneficiary Bank Code/SWIFT Code, Routing Code Type 1 - Transit Code, Routing Code Value 1 | L77: Remitter Beneficiary Relationship, Nature of Business, Duration of Contract, Commercial Agreement, Current Invoice | M77: Remitter Name and Statement Narrative is passed to the Beneficiary Bank and depends on Beneficiary Bank if it appears in the Beneficiary statement narration. | O77: Clients wanting to do payment via INTERAC should reach out to their NIUM representative | P77: 0 | Q77: 0 | R77: 0 | S77: 0 | T77: CAD 25,000 | U77: CAD 25,000 | V77: CAD 25,000 | W77: CAD 25,000
A78: Cape Verde | B78: Foreign Currency Wire Transfer (SWIFT) | C78: USD, EUR, SGD, GBP, AUD, CAD, HKD, JPY, CHF, NZD | D78: T1 | E78: B2B, B2P, P2P, P2B | F78: B2B, B2P, P2P, P2B | G78: USD, EUR, SGD, GBP, AUD, CAD, HKD, JPY, CHF, NZD | H78: Bank | I78: All SWIFT enabled banks in the country | J78: Same-day processing subject to cutoff of 07:30 UTC | K78: Remitter Name, Remitter Account Type, Remitter Identification Type, Remitter Identification Number, Remitter Address, Remitter Country Code, Beneficiary Name, Beneficiary Account Type, Beneficiary Account Number, Beneficiary Country Code, Beneficiary Address (Recommended), Beneficiary City (Recommended), Beneficiary Postcode (Recommended), Routing Code Value 1, Routing Code Type 1 - SWIFT Code, Remit Purpose Code | L78: Remitter Beneficiary Relationship, Nature of Business, Duration of Contract, Commercial Agreement, Current Invoice | M78: Ultimate Sender Name and narrative details will be passed as part of MT103 message to beneficiary bank.Details available on beneficiary statement will be dependent on beneficiary bank. | N78: MT103 can be considered as a proof of payment and can be provided on request | O78: WIRES can be sent to all countries except for OFAC listed.MT103 can be provided on request.For foreign currency wire currencies USD, EUR, GBP - NIUM supports both OUR and SHA fee type while for other currencies AUD, CAD, CHF, JPY, NZD, HKD, SGD - NIUM supports only SHA fee typeProcessing of payments to Crimea, Donetsk, Luhansk, Sevastopol regions of Ukraine is prohibited. This list is subject to change. | P78: 0 | Q78: 0 | R78: 0 | S78: 0 | T78: No limit | U78: No limit | V78: No limit | W78: No limit
A79: Cape Verde | B79: Visa Direct | C79: CVE | D79: T2 | E79: B2B, B2P, P2P, P2B | F79: B2B, B2P, P2P, P2B | G79: CVE | H79: VISA | J79: 1. 24x7 Availability2. Real-time for Fast fund Enabled (Details on fast-fund enabled countries available on request)3. T+2 for other countries | K79: Remitter Name, Remitter Identification Type, Remitter Identification Number, Remitter Country Code, Beneficiary Card Number, Beneficiary Name, Beneficiary Country Code | O79: For more information, please contact your NIUM account manager team. Additional information and approval from VISA is required before this payout method can be made available.Origination of funds is allowed only from a set of countries as mentioned in the table below.In case the transaction currency does not match the destination card issuer currency, amount will be converted and credited in currency of the card issuer.In few countries, only few banks may allow the transactions.Below additional daily/monthly/yearly limits applicable for P2P transactions whichever reached first Per Day - 30 transactions or USD 10,000 per Beneficiary card Per Week - 50 transactions or USD 25,000 per Beneficiary card Per Month - 150 transactions or USD 50,000 per Beneficiary card.Below additional daily/monthly/yearly limits applicable for B2P/B2B transactions whichever reached first Per Day - 30 transactions or USD 50,000 per Beneficiary card Per Week - 50 transactions or USD 100,000 per Beneficiary card Per Month - 150 transactions or USD 200,000 per Beneficiary card. | P79: 0 | Q79: 0 | R79: 0 | S79: 0 | T79: USD 50,000 | U79: USD 50,000 | V79: USD 2,500 | W79: USD 50,000
A80: Cayman Islands | B80: Foreign Currency Wire Transfer (SWIFT) | C80: USD, EUR, SGD, GBP, AUD, CAD, HKD, JPY, CHF, NZD | D80: T1 | E80: B2B, B2P, P2P, P2B | F80: B2B, B2P, P2P, P2B | G80: USD, EUR, SGD, GBP, AUD, CAD, HKD, JPY, CHF, NZD | H80: Bank | I80: All SWIFT enabled banks in the country | J80: Same-day processing subject to cutoff of 07:30 UTC | K80: Remitter Name, Remitter Account Type, Remitter Identification Type, Remitter Identification Number, Remitter Address, Remitter Country Code, Beneficiary Name, Beneficiary Account Type, Beneficiary Account Number, Beneficiary Country Code, Beneficiary Address (Recommended), Beneficiary City (Recommended), Beneficiary Postcode (Recommended), Routing Code Value 1, Routing Code Type 1 - SWIFT Code, Remit Purpose Code | L80: Remitter Beneficiary Relationship, Nature of Business, Duration of Contract, Commercial Agreement, Current Invoice | M80: Ultimate Sender Name and narrative details will be passed as part of MT103 message to beneficiary bank.Details available on beneficiary statement will be dependent on beneficiary bank. | N80: MT103 can be considered as a proof of payment and can be provided on request | O80: WIRES can be sent to all countries except for OFAC listed.MT103 can be provided on request.For foreign currency wire currencies USD, EUR, GBP - NIUM supports both OUR and SHA fee type while for other currencies AUD, CAD, CHF, JPY, NZD, HKD, SGD - NIUM supports only SHA fee typeProcessing of payments to Crimea, Donetsk, Luhansk, Sevastopol regions of Ukraine is prohibited. This list is subject to change. | P80: 0 | Q80: 0 | R80: 0 | S80: 0 | T80: No limit | U80: No limit | V80: No limit | W80: No limit
A81: Chad | B81: Foreign Currency Wire Transfer (SWIFT) | C81: USD, EUR, SGD, GBP, AUD, CAD, HKD, JPY, CHF, NZD | D81: T1 | E81: B2B, B2P, P2P, P2B | F81: B2B, B2P, P2P, P2B | G81: USD, EUR, SGD, GBP, AUD, CAD, HKD, JPY, CHF, NZD | H81: Bank | I81: All SWIFT enabled banks in the country | J81: Same-day processing subject to cutoff of 07:30 UTC | K81: Remitter Name, Remitter Account Type, Remitter Identification Type, Remitter Identification Number, Remitter Address, Remitter Country Code, Beneficiary Name, Beneficiary Account Type, Beneficiary Account Number, Beneficiary Country Code, Beneficiary Address, Beneficiary City, Beneficiary Postcode, Routing Code Value 1, Routing Code Type 1 - SWIFT Code, Remit Purpose Code | L81: Remitter Beneficiary Relationship, Nature of Business, Duration of Contract, Commercial Agreement, Current Invoice | M81: Ultimate Sender Name and narrative details will be passed as part of MT103 message to beneficiary bank.Details available on beneficiary statement will be dependent on beneficiary bank. | N81: MT103 can be considered as a proof of payment and can be provided on request | O81: WIRES can be sent to all countries except for OFAC listed.MT103 can be provided on request.NIUM does not support OUR charge type for CAD currency WIRESProcessing of payments to Crimea, Donetsk, Luhansk, Sevastopol regions of Ukraine is prohibited. This list is subject to change. | P81: 0 | Q81: 0 | R81: 0 | S81: 0 | T81: No limit | U81: No limit | V81: No limit | W81: No limit
A82: Chile | B82: Bank Account (ACH) | C82: CLP | D82: T0 | E82: B2B, B2P, P2P, P2B | F82: B2B, B2P, P2P, P2B | G82: CLP | H82: Partner | I82: All banks in Chile | J82: Same day credit subject to cutoff of 15:00 BRT | K82: Remitter Name, Remitter Identification Type, Remitter Address, Beneficiary Name, Beneficiary Country Code, Beneficiary Account Number, Routing Code Value 1, Routing Code Type 1 - SWIFT CODE, Remitter Account Type, Remitter Identification Number, Remitter Country Code, Beneficiary Account Type, Beneficiary Bank Account Type, Beneficiary Identification Type, Beneficiary Identification Value, Remit Purpose Code | L82: Remitter Beneficiary Relationship, Nature of Business, Duration of Contract, Commercial Agreement, Current Invoice | M82: Domestic Clearing System limits ability to transfer full remitter information to the Beneficiary. Visibility of Standard Statement Narration is missing. | P82: CLP 1 | Q82: CLP 1 | R82: CLP 1 | S82: CLP 1 | T82: No limit | U82: No limit | V82: No limit | W82: No limit
A83: Chile | B83: Foreign Currency Wire Transfer (SWIFT) | C83: USD, EUR, SGD, GBP, AUD, CAD, HKD, JPY, CHF, NZD | D83: T1 | E83: B2B, B2P, P2P, P2B | F83: B2B, B2P, P2P, P2B | G83: USD, EUR, SGD, GBP, AUD, CAD, HKD, JPY, CHF, NZD | H83: Bank | I83: All SWIFT enabled banks in the country | J83: Same-day processing subject to cutoff of 07:30 UTC | K83: Remitter Name, Remitter Account Type, Remitter Identification Type, Remitter Identification Number, Remitter Address, Remitter Country Code, Beneficiary Name, Beneficiary Account Type, Beneficiary Account Number, Beneficiary Country Code, Beneficiary Address (Recommended), Beneficiary City (Recommended), Beneficiary Postcode (Recommended), Routing Code Value 1, Routing Code Type 1 - SWIFT Code, Remit Purpose Code | L83: Remitter Beneficiary Relationship, Nature of Business, Duration of Contract, Commercial Agreement, Current Invoice | M83: Ultimate Sender Name and narrative details will be passed as part of MT103 message to beneficiary bank.Details available on beneficiary statement will be dependent on beneficiary bank. | N83: MT103 can be considered as a proof of payment and can be provided on request | O83: WIRES can be sent to all countries except for OFAC listed.MT103 can be provided on request.For foreign currency wire currencies USD, EUR, GBP - NIUM supports both OUR and SHA fee type while for other currencies AUD, CAD, CHF, JPY, NZD, HKD, SGD - NIUM supports only SHA fee typeProcessing of payments to Crimea, Donetsk, Luhansk, Sevastopol regions of Ukraine is prohibited. This list is subject to change. | P83: 0 | Q83: 0 | R83: 0 | S83: 0 | T83: No limit | U83: No limit | V83: No limit | W83: No limit
A84: China | B84: Bank Account (ACH) | C84: CNY | D84: Realtime | E84: B2B, P2B | F84: B2B, P2B | G84: CNY | H84: Partner | I84: Major banks in China | J84: Sameday delivery subject to local timezone | K84: Remitter Name, Remitter Identification Type, Remitter Identification Number, Remitter Account Type, Remitter Address, Remitter Country Code, Beneficiary Name, Beneficiary Account Number, Beneficiary Identification Value, Beneficiary Account Type, Beneficiary Country Code, Order Number, Order Amount, Order Trade Time, Order Commodity, Goods Quantity, Routing Code ValueÂ (SWIFT Code or Beneficiary Bank Code or Beneficiary Bank Name), Beneficiary Bank Name (Required only if Bank code or SWIFT code not sent) Logistics Name, Remit Purpose Code, Destination Currency (CNY), Destination Amount | L84: Remitter Beneficiary Relationship, Nature of Business, Duration of Contract, Commercial Agreement, Current Invoice | M84: Domestic Clearing System limits ability to transfer full remitter information to the Beneficiary. Visibility of Standard Statement Narration is missing. | O84: Please reach out to your NIUM representative for getting this capability enabled and for detailed technical specifications | P84: CNY 1 | Q84: Not Supported | R84: Not Supported | S84: CNY 1 | T84: No limit | U84: Not Supported | V84: Not Supported | W84: No limit
A85: China | B85: Foreign Currency Wire Transfer (SWIFT) | C85: USD, EUR, SGD, GBP, AUD, CAD, HKD, JPY, CHF, NZD | D85: T1 | E85: B2B, B2P, P2P, P2B | F85: B2B, B2P, P2P, P2B | G85: USD, EUR, SGD, GBP, AUD, CAD, HKD, JPY, CHF, NZD | H85: Bank | I85: All SWIFT enabled banks in the country | J85: Same-day processing subject to cutoff of 07:30 UTC | K85: Remitter Name, Remitter Account Type, Remitter Identification Type, Remitter Identification Number, Remitter Address, Remitter Country Code, Beneficiary Name, Beneficiary Account Type, Beneficiary Account Number, Beneficiary Country Code, Beneficiary Address, Beneficiary City, Beneficiary Postcode, Routing Code Value 1, Routing Code Type 1 - SWIFT Code, Remit Purpose Code | L85: Remitter Beneficiary Relationship, Nature of Business, Duration of Contract, Commercial Agreement, Current Invoice | M85: Ultimate Sender Name and narrative details will be passed as part of MT103 message to beneficiary bank.Details available on beneficiary statement will be dependent on beneficiary bank. | N85: MT103 can be considered as a proof of payment and can be provided on request | O85: WIRES can be sent to all countries except for OFAC listed.MT103 can be provided on request.NIUM does not support OUR charge type for CAD currency WIRESProcessing of payments to Crimea, Donetsk, Luhansk, Sevastopol regions of Ukraine is prohibited. This list is subject to change. | P85: 0 | Q85: 0 | R85: 0 | S85: 0 | T85: No limit | U85: No limit | V85: No limit | W85: No limit
A86: China | B86: Local Currency Wire Transfer | C86: CNY | D86: T1 | E86: B2B, B2P, P2P, P2B | F86: B2B, B2P, P2P, P2B | G86: CNY | H86: Bank | I86: All major banks enabled with SWIFT. | J86: Same-day processing subject to cutoff of 7:30 UTC | K86: Remitter Name, Remitter Account Type, Remitter Identification Type, Remitter Identification Number, Remitter Address, Remitter Country code, Remit Purpose Code, Beneficiary Name, Beneficiary Account Number, Beneficiary Account Type, Beneficiary Country Code, Beneficiary Address, Beneficiary City, Beneficiary Postcode, Routing Code Type 1- SWIFT CODE, Routing Code Value | L86: Remitter Beneficiary Relationship, Nature of Business, Duration of Contract, Commercial Agreement, Current Invoice | M86: Ultimate Sender Name and narrative details will be passed as part of MT103 message to beneficiary bank.Details available on beneficiary statement will be dependent on beneficiary bank. | N86: MT103 can be considered as a proof of payment and can be provided on request | O86: Additional documentation may be requested by beneficiary bank to validate underlying transaction and receive credit into account. For WIRES, NIUM supports transactions with SHA Fee Type. | P86: 0 | Q86: 0 | R86: 0 | S86: 0 | T86: No limit | U86: No limit | V86: No limit | W86: No limit
A87: China | B87: Union Pay Card (CARD) | C87: CNY | D87: Realtime | E87: B2P, P2P | F87: B2P, P2P | G87: CNY | H87: Partner | I87: All major banks in Mainland China (List Available) | J87: Real Time credit subject to cut-off window 08:00 to 22:00 local time 17 Banks - 5,000 USD per transaction,10,000 USD per day,50,000 USD per year | K87: Remitter Name, Remitter Account Type, Remitter Identification number, Remitter Identification Type, Remitter Address, Remitter Country Code, Beneficiary Name, Beneficiary Country Code, Beneficiary UPI Card Number, Beneficiary ID Type, Beneficiary ID Number, Beneficiary Account Type, Beneficiary Address | L87: Remitter Beneficiary Relationship, Nature of Business, Duration of Contract, Commercial Agreement, Current Invoice | M87: For Real time credit to 17 Banks - Beneficiary can see "Instarem" in their transaction details. | O87: For the Realtime Transactions - Minor positive differences in the amount credited to bene is possible.The beneficiary must be a Chinese National from Mainland China. | P87: Not Supported | Q87: 0 | R87: 0 | S87: Not Supported | T87: Not Supported | U87: USD 3,000 | V87: USD 3,000 | W87: Not Supported
A88: China | B88: Visa Direct | C88: CNY | D88: T2 | E88: B2B, B2P, P2P, P2B | F88: B2B, B2P, P2P, P2B | G88: CNY | H88: VISA | J88: 1. 24x7 Availability2. Real-time for Fast fund Enabled (Details on fast-fund enabled countries available on request)3. T+2 for other countries | K88: Remitter Name, Remitter Identification Type, Remitter Identification Number, Remitter Country Code, Beneficiary Card Number, Beneficiary Name, Beneficiary Country Code | O88: For more information, please contact your NIUM account manager team. Additional information and approval from VISA is required before this payout method can be made available.Origination of funds is allowed only from a set of countries as mentioned in the table below.In case the transaction currency does not match the destination card issuer currency, amount will be converted and credited in currency of the card issuer.In few countries, only few banks may allow the transactions.Below additional daily/monthly/yearly limits applicable for P2P transactions whichever reached first Per Day - 30 transactions or USD 10,000 per Beneficiary card Per Week - 50 transactions or USD 25,000 per Beneficiary card Per Month - 150 transactions or USD 50,000 per Beneficiary card.Below additional daily/monthly/yearly limits applicable for B2P/B2B transactions whichever reached first Per Day - 30 transactions or USD 50,000 per Beneficiary card Per Week - 50 transactions or USD 100,000 per Beneficiary card Per Month - 150 transactions or USD 200,000 per Beneficiary card. | P88: 0 | Q88: 0 | R88: 0 | S88: 0 | T88: USD 50,000 | U88: USD 50,000 | V88: USD 2,500 | W88: USD 50,000
A89: China | B89: Wallet | C89: CNY | D89: Realtime | E89: P2P | F89: P2P | G89: CNY | H89: Partner | I89: Via all KYC Completed Alipay Wallets | J89: Realtime, 24x7 | K89: Remitter Name, Remitter Account Type, Remitter Identification Number, Remitter Identification Type, Remitter Address, Remitter Country Code, Remitter Date of Birth, Remitter Nationality, Beneficiary Name, Beneficiary Country Code, Beneficiary Alipay Wallet ID, Beneficiary Account Type, Remit Purpose Code, Payout Method - WALLET | L89: Remitter Beneficiary Relationship, Nature of Business, Duration of Contract, Commercial Agreement, Current Invoice | M89: Sender Name will be visible in the Beneficiary"s wallet entry. | O89: Online Bene Registration on Alipay App (one-time per Bene) & Payment acceptance (per transaction) to be done in 72 Hrs.Beneficiary must be a Chinese National from Mainland China. | P89: Not Supported | Q89: Not Supported | R89: 0 | S89: Not Supported | T89: Not Supported | U89: Not Supported | V89: CNY 50,000 | W89: Not Supported
A90: Christmas Island | B90: Foreign Currency Wire Transfer (SWIFT) | C90: USD, EUR, SGD, GBP, AUD, CAD, HKD, JPY, CHF, NZD | D90: T1 | E90: B2B, B2P, P2P, P2B | F90: B2B, B2P, P2P, P2B | G90: USD, EUR, SGD, GBP, AUD, CAD, HKD, JPY, CHF, NZD | H90: Bank | I90: All SWIFT enabled banks in the country | J90: Same-day processing subject to cutoff of 07:30 UTC | K90: Remitter Name, Remitter Account Type, Remitter Identification Type, Remitter Identification Number, Remitter Address, Remitter Country Code, Beneficiary Name, Beneficiary Account Type, Beneficiary Account Number, Beneficiary Country Code, Beneficiary Address, Beneficiary City, Beneficiary Postcode, Routing Code Value 1, Routing Code Type 1 - SWIFT Code, Remit Purpose Code | L90: Remitter Beneficiary Relationship, Nature of Business, Duration of Contract, Commercial Agreement, Current Invoice | M90: Ultimate Sender Name and narrative details will be passed as part of MT103 message to beneficiary bank.Details available on beneficiary statement will be dependent on beneficiary bank. | N90: MT103 can be considered as a proof of payment and can be provided on request | O90: WIRES can be sent to all countries except for OFAC listed.MT103 can be provided on request.NIUM does not support OUR charge type for CAD currency WIRESProcessing of payments to Crimea, Donetsk, Luhansk, Sevastopol regions of Ukraine is prohibited. This list is subject to change. | P90: 0 | Q90: 0 | R90: 0 | S90: 0 | T90: No limit | U90: No limit | V90: No limit | W90: No limit
A91: Colombia | B91: Bank Account (ACH) | C91: COP | D91: T0 | E91: B2B, B2P, P2P, P2B | F91: B2B, B2P, P2P, P2B | G91: COP | H91: Partner | I91: All banks in Colombia | J91: Same day credit subject to cutoff of 18:00 UTC | K91: Remitter Name, Remitter Identification Type, Remitter Address, Beneficiary Name, Beneficiary Country Code, Beneficiary Account Number, Routing Code Value 1, Routing Code Type 1 - SWIFT CODE, Remitter Account Type, Remitter Identification Number, Remitter Country Code, Beneficiary Account Type, Beneficiary Bank Account Type, Beneficiary Identification Type, Beneficiary Identification Value, Remit Purpose Code | L91: Remitter Beneficiary Relationship, Nature of Business, Duration of Contract, Commercial Agreement, Current Invoice | M91: Domestic Clearing System limits ability to transfer full remitter information to the Beneficiary. Visibility of Standard Statement Narration is missing. | P91: COP 1 | Q91: COP 1 | R91: COP 1 | S91: COP 1 | T91: No limit | U91: No limit | V91: No limit | W91: No limit
A92: Colombia | B92: Foreign Currency Wire Transfer (SWIFT) | C92: USD, EUR, SGD, GBP, AUD, CAD, HKD, JPY, CHF, NZD | D92: T1 | E92: B2B, B2P, P2P, P2B | F92: B2B, B2P, P2P, P2B | G92: USD, EUR, SGD, GBP, AUD, CAD, HKD, JPY, CHF, NZD | H92: Bank | I92: All SWIFT enabled banks in the country | J92: Same-day processing subject to cutoff of 07:30 UTC | K92: Remitter Name, Remitter Account Type, Remitter Identification Type, Remitter Identification Number, Remitter Address, Remitter Country Code, Beneficiary Name, Beneficiary Account Type, Beneficiary Account Number, Beneficiary Country Code, Beneficiary Address, Beneficiary City, Beneficiary Postcode, Routing Code Value 1, Routing Code Type 1 - SWIFT Code, Remit Purpose Code | L92: Remitter Beneficiary Relationship, Nature of Business, Duration of Contract, Commercial Agreement, Current Invoice | M92: Ultimate Sender Name and narrative details will be passed as part of MT103 message to beneficiary bank.Details available on beneficiary statement will be dependent on beneficiary bank. | N92: MT103 can be considered as a proof of payment and can be provided on request | O92: WIRES can be sent to all countries except for OFAC listed.MT103 can be provided on request.NIUM does not support OUR charge type for CAD currency WIRESProcessing of payments to Crimea, Donetsk, Luhansk, Sevastopol regions of Ukraine is prohibited. This list is subject to change. | P92: 0 | Q92: 0 | R92: 0 | S92: 0 | T92: No limit | U92: No limit | V92: No limit | W92: No limit
A93: Comoros | B93: Foreign Currency Wire Transfer (SWIFT) | C93: USD, EUR, SGD, GBP, AUD, CAD, HKD, JPY, CHF, NZD | D93: T1 | E93: B2B, B2P, P2P, P2B | F93: B2B, B2P, P2P, P2B | G93: USD, EUR, SGD, GBP, AUD, CAD, HKD, JPY, CHF, NZD | H93: Bank | I93: All SWIFT enabled banks in the country | J93: Same-day processing subject to cutoff of 07:30 UTC | K93: Remitter Name, Remitter Account Type, Remitter Identification Type, Remitter Identification Number, Remitter Address, Remitter Country Code, Beneficiary Name, Beneficiary Account Type, Beneficiary Account Number, Beneficiary Country Code, Beneficiary Address, Beneficiary City, Beneficiary Postcode, Routing Code Value 1, Routing Code Type 1 - SWIFT Code, Remit Purpose Code | L93: Remitter Beneficiary Relationship, Nature of Business, Duration of Contract, Commercial Agreement, Current Invoice | M93: Ultimate Sender Name and narrative details will be passed as part of MT103 message to beneficiary bank.Details available on beneficiary statement will be dependent on beneficiary bank. | N93: MT103 can be considered as a proof of payment and can be provided on request | O93: WIRES can be sent to all countries except for OFAC listed.MT103 can be provided on request.NIUM does not support OUR charge type for CAD currency WIRESProcessing of payments to Crimea, Donetsk, Luhansk, Sevastopol regions of Ukraine is prohibited. This list is subject to change. | P93: 0 | Q93: 0 | R93: 0 | S93: 0 | T93: No limit | U93: No limit | V93: No limit | W93: No limit
A94: Comoros | B94: Visa Direct | C94: KMF | D94: Realtime | E94: B2B, B2P, P2P, P2B | F94: B2B, B2P, P2P, P2B | G94: KMF | H94: VISA | J94: 1. 24x7 Availability2. Real-time for Fast fund Enabled (Details on fast-fund enabled countries available on request)3. T+2 for other countries | K94: Remitter Name, Remitter Identification Type, Remitter Identification Number, Remitter Country Code, Beneficiary Card Number, Beneficiary Name, Beneficiary Country Code | O94: For more information, please contact your NIUM account manager team. Additional information and approval from VISA is required before this payout method can be made available.Origination of funds is allowed only from a set of countries as mentioned in the table below.In case the transaction currency does not match the destination card issuer currency, amount will be converted and credited in currency of the card issuer.In few countries, only few banks may allow the transactions.Below additional daily/monthly/yearly limits applicable for P2P transactions whichever reached first Per Day - 30 transactions or USD 10,000 per Beneficiary card Per Week - 50 transactions or USD 25,000 per Beneficiary card Per Month - 150 transactions or USD 50,000 per Beneficiary card.Below additional daily/monthly/yearly limits applicable for B2P/B2B transactions whichever reached first Per Day - 30 transactions or USD 50,000 per Beneficiary card Per Week - 50 transactions or USD 100,000 per Beneficiary card Per Month - 150 transactions or USD 200,000 per Beneficiary card. | P94: 0 | Q94: 0 | R94: 0 | S94: 0 | T94: USD 50,000 | U94: USD 50,000 | V94: USD 2,500 | W94: USD 50,000
A95: Cook Islands | B95: Foreign Currency Wire Transfer (SWIFT) | C95: USD, EUR, SGD, GBP, AUD, CAD, HKD, JPY, CHF, NZD | D95: T1 | E95: B2B, B2P, P2P, P2B | F95: B2B, B2P, P2P, P2B | G95: USD, EUR, SGD, GBP, AUD, CAD, HKD, JPY, CHF, NZD | H95: Bank | I95: All SWIFT enabled banks in the country | J95: Same-day processing subject to cutoff of 07:30 UTC | K95: Remitter Name, Remitter Account Type, Remitter Identification Type, Remitter Identification Number, Remitter Address, Remitter Country Code, Beneficiary Name, Beneficiary Account Type, Beneficiary Account Number, Beneficiary Country Code, Beneficiary Address, Beneficiary City, Beneficiary Postcode, Routing Code Value 1, Routing Code Type 1 - SWIFT Code, Remit Purpose Code | L95: Remitter Beneficiary Relationship, Nature of Business, Duration of Contract, Commercial Agreement, Current Invoice | M95: Ultimate Sender Name and narrative details will be passed as part of MT103 message to beneficiary bank.Details available on beneficiary statement will be dependent on beneficiary bank. | N95: MT103 can be considered as a proof of payment and can be provided on request | O95: WIRES can be sent to all countries except for OFAC listed.MT103 can be provided on request.NIUM does not support OUR charge type for CAD currency WIRESProcessing of payments to Crimea, Donetsk, Luhansk, Sevastopol regions of Ukraine is prohibited. This list is subject to change. | P95: 0 | Q95: 0 | R95: 0 | S95: 0 | T95: No limit | U95: No limit | V95: No limit | W95: No limit
A96: Costa Rica | B96: Bank Account (ACH) | C96: CRC | D96: T0 | E96: B2B, B2P, P2B | F96: B2B, B2P, P2B | G96: CRC | H96: Partner | I96: All major banks in Costa Rica | J96: 15:00 UTC on business days | K96: Remitter Name, Remitter Account Type, Remitter Country Code, Remit Purpose Code, Remitter Identification Type, Remitter Identification Number, Beneficiary Name, Beneficiary Address, Beneficiary Country Code, Beneficiary Bank Account Type, Beneficiary Account Type, Beneficiary Account Number, Beneficiary Identification Type, Beneficiary Identification Value | M96: Clearing system limits control on beneficiary statement narrative. | P96: CRC 0.01 | Q96: CRC 0.01 | R96: Not Supported | S96: CRC 0.01 | T96: No limit | U96: No limit | V96: Not Supported | W96: No limit
A97: Costa Rica | B97: Foreign Currency Wire Transfer (SWIFT) | C97: USD, EUR, SGD, GBP, AUD, CAD, HKD, JPY, CHF, NZD | D97: T1 | E97: B2B, B2P, P2P, P2B | F97: B2B, B2P, P2P, P2B | G97: USD, EUR, SGD, GBP, AUD, CAD, HKD, JPY, CHF, NZD | H97: Bank | I97: All SWIFT enabled banks in the country | J97: Same-day processing subject to cutoff of 07:30 UTC | K97: Remitter Name, Remitter Account Type, Remitter Identification Type, Remitter Identification Number, Remitter Address, Remitter Country Code, Beneficiary Name, Beneficiary Account Type, Beneficiary Account Number, Beneficiary Country Code, Beneficiary Address, Beneficiary City, Beneficiary Postcode, Routing Code Value 1, Routing Code Type 1 - SWIFT Code, Remit Purpose Code | L97: Remitter Beneficiary Relationship, Nature of Business, Duration of Contract, Commercial Agreement, Current Invoice | M97: Ultimate Sender Name and narrative details will be passed as part of MT103 message to beneficiary bank.Details available on beneficiary statement will be dependent on beneficiary bank. | N97: MT103 can be considered as a proof of payment and can be provided on request | O97: WIRES can be sent to all countries except for OFAC listed.MT103 can be provided on request.NIUM does not support OUR charge type for CAD currency WIRESProcessing of payments to Crimea, Donetsk, Luhansk, Sevastopol regions of Ukraine is prohibited. This list is subject to change. | P97: 0 | Q97: 0 | R97: 0 | S97: 0 | T97: No limit | U97: No limit | V97: No limit | W97: No limit
A98: CuraÃ§ao | B98: Foreign Currency Wire Transfer (SWIFT) | C98: USD, EUR, SGD, GBP, AUD, CAD, HKD, JPY, CHF, NZD | D98: T1 | E98: B2B, B2P, P2P, P2B | F98: B2B, B2P, P2P, P2B | G98: USD, EUR, SGD, GBP, AUD, CAD, HKD, JPY, CHF, NZD | H98: Bank | I98: All SWIFT enabled banks in the country | J98: Same-day processing subject to cutoff of 07:30 UTC | K98: Remitter Name, Remitter Account Type, Remitter Identification Type, Remitter Identification Number, Remitter Address, Remitter Country Code, Beneficiary Name, Beneficiary Account Type, Beneficiary Account Number, Beneficiary Country Code, Beneficiary Address, Beneficiary City, Beneficiary Postcode, Routing Code Value 1, Routing Code Type 1 - SWIFT Code, Remit Purpose Code | L98: Remitter Beneficiary Relationship, Nature of Business, Duration of Contract, Commercial Agreement, Current Invoice | M98: Ultimate Sender Name and narrative details will be passed as part of MT103 message to beneficiary bank.Details available on beneficiary statement will be dependent on beneficiary bank. | N98: MT103 can be considered as a proof of payment and can be provided on request | O98: WIRES can be sent to all countries except for OFAC listed.MT103 can be provided on request.NIUM does not support OUR charge type for CAD currency WIRESProcessing of payments to Crimea, Donetsk, Luhansk, Sevastopol regions of Ukraine is prohibited. This list is subject to change. | P98: 0 | Q98: 0 | R98: 0 | S98: 0 | T98: No limit | U98: No limit | V98: No limit | W98: No limit
A99: Cyprus | B99: Bank Account (SEPA) | C99: EUR | D99: Realtime | E99: B2B, B2P, P2P, P2B | F99: B2B, B2P, P2P, P2B | G99: EUR | H99: Bank | I99: All banks connected with SEPA Network | J99: 1. Real-time for transaction amount <= EUR 100,0002. Same-day for transaction amount > EUR 100,000 subject to cutoff of 14.00 EET | K99: Remitter Name, Remitter Account Type, Remitter Address, Remitter Country Code, Remitter Identification Type, Remitter Identification Number, Remit Purpose Code, Remitter City, Remitter Postcode, Beneficiary Name, Beneficiary Country Code, Beneficiary Account Type, Beneficiary Account Number - IBAN, Routing Code Type 1 - SWIFT CODE, Routing Code Value 1 | L99: Remitter Beneficiary Relationship, Nature of Business, Duration of Contract, Commercial Agreement, Current Invoice | M99: Remitter Name & NIUM appears in the beneficiary statement | N99: Upon request, Proof of Payment for a transaction can be made available. | O99: 1. Coverage includes the EU as well as several Non-EU countries.2. Not all supported countries support Realtime payments3. Few banks in Instant supported countries may not support instant payments and payments will be routed through Standard mode in such cases.4.Certain banks require the complete 11-character SWIFT codeâ€”including the branch identifierâ€”in order to accurately route and successfully process the payment. | P99: EUR 0.01 | Q99: EUR 0.01 | R99: EUR 0.01 | S99: EUR 0.01 | T99: No limit | U99: No limit | V99: No limit | W99: No limit
A100: Cyprus | B100: Foreign Currency Wire Transfer (SWIFT) | C100: USD, EUR, SGD, GBP, AUD, CAD, HKD, JPY, CHF, NZD | D100: T1 | E100: B2B, B2P, P2P, P2B | F100: B2B, B2P, P2P, P2B | G100: USD, EUR, SGD, GBP, AUD, CAD, HKD, JPY, CHF, NZD | H100: Bank | I100: All SWIFT enabled banks in the country | J100: Same-day processing subject to cutoff of 07:30 UTC | K100: Remitter Name, Remitter Account Type, Remitter Identification Type, Remitter Identification Number, Remitter Address, Remitter Country Code, Beneficiary Name, Beneficiary Account Type, Beneficiary Account Number, Beneficiary Country Code, Beneficiary Address (Recommended), Beneficiary City (Recommended), Beneficiary Postcode (Recommended), Routing Code Value 1, Routing Code Type 1 - SWIFT Code, Remit Purpose Code | L100: Remitter Beneficiary Relationship, Nature of Business, Duration of Contract, Commercial Agreement, Current Invoice | M100: Ultimate Sender Name and narrative details will be passed as part of MT103 message to beneficiary bank.Details available on beneficiary statement will be dependent on beneficiary bank. | N100: MT103 can be considered as a proof of payment and can be provided on request | O100: WIRES can be sent to all countries except for OFAC listed.MT103 can be provided on request.For foreign currency wire currencies USD, EUR, GBP - NIUM supports both OUR and SHA fee type while for other currencies AUD, CAD, CHF, JPY, NZD, HKD, SGD - NIUM supports only SHA fee typeProcessing of payments to Crimea, Donetsk, Luhansk, Sevastopol regions of Ukraine is prohibited. This list is subject to change. | P100: 0 | Q100: 0 | R100: 0 | S100: 0 | T100: No limit | U100: No limit | V100: No limit | W100: No limit
...

Sheet Sheet2
A1: AED | B1: =VLOOKUP(A1,Sheet1!C:C,1,0) -> AED
A2: ARS | B2: =VLOOKUP(A2,Sheet1!C:C,1,0) -> ARS
A3: AUD | B3: =VLOOKUP(A3,Sheet1!C:C,1,0) -> AUD
A4: BGN | B4: =VLOOKUP(A4,Sheet1!C:C,1,0) -> BGN
A5: BRL | B5: =VLOOKUP(A5,Sheet1!C:C,1,0) -> BRL
A6: CAD | B6: =VLOOKUP(A6,Sheet1!C:C,1,0) -> CAD
A7: CHF | B7: =VLOOKUP(A7,Sheet1!C:C,1,0) -> #N/A
A8: CLP | B8: =VLOOKUP(A8,Sheet1!C:C,1,0) -> CLP
A9: CNY | B9: =VLOOKUP(A9,Sheet1!C:C,1,0) -> CNY
A10: COP | B10: =VLOOKUP(A10,Sheet1!C:C,1,0) -> COP
A11: CZK | B11: =VLOOKUP(A11,Sheet1!C:C,1,0) -> CZK
A12: DKK | B12: =VLOOKUP(A12,Sheet1!C:C,1,0) -> DKK
... A41: ZAR | B41: =VLOOKUP(A41,Sheet1!C:C,1,0) -> ZAR
